Workbook
Name Slicer_Cleaned_Region: #N/A
Name Slicer_Month: #N/A

Sheet Raw Sales Data
A1: Order ID | B1: Order Date | C1: Region | D1: Sales Rep | E1: Product ID | F1: Product Name | G1: Quantity | H1: Unit Price (KES)
A2: 10008 | B2: 45306 | C2: mombasa | D2: Peter Otieno | E2: P013 | F2: Kitchen Knife Set | G2: 20 | H2: 1350
A3: 10300 | B3: 2024.03.13 | C3: nakuru | D3: Faith Wanjiru | E3: P013 | F3: Kitchen Knife Set | G3: 6 | H3: 1350
A4: 10328 | B4: 45338 | C4: Mombasa | D4: Grace Achieng | E4: P001 | F4: 20L Jerrycan - Blue | G4: 4 | H4: 600
A5: 10216 | B5: 45373 | C5: Eldoret | D5: grace achieng | E5: P015 | F5: Water Dispenser Stand | G5: 10 | H5: 2300
A6: 10065 | B6: 45505 | C6: KISUMU | D6: Mercy Njeri | E6: P006 | F6: Plastic Storage Basket L | G6: 8 | H6: 420
A7: 10222 | B7: 45339 | C7: Mombasa | D7: aisha hassan | E7: P001 | F7: 20L Jerrycan - Blue | G7: 5 | H7: 600
A8: 10140 | B8: 15/01/2024 | C8: Thika | D8: Faith Wanjiru | E8: P012 | F8: Garden Hose 20m | G8: 15 | H8: 1750
A9: 10268 | B9: 2024.02.14 | C9: Mombasa | D9: Faith Wanjiru | E9: P011 | F9: PADLOCK SET (3PC) | G9: 6 | H9: 700
A10: 10025 | B10: 45323 | C10: Kisumu | D10: PETER OTIENO | E10: P013 | F10: Kitchen Knife Set | G10: 2 | H10: 1350
A11: 10205 | B11: 45599 | C11: MOMBASA | D11: Grace Achieng | E11: P008 | F11: USB Wall Charger UC-5 | G11: 2 | H11: 500
A12: 10188 | B12: 45370 | C12: Thika | D12: Peter Otieno | E12: P008 | F12: USB Wall Charger UC-5 | G12: 6 | H12: 500
A13: 10152 | B13: 45321 | C13: Nakuru | D13: faith wanjiru | E13: P008 | F13: USB Wall Charger UC-5 | G13: 12 | H13: 500
A14: 10137 | B14: 45325 | C14: Nakuru | D14: Faith Wanjiru | E14: P008 | F14: USB Wall Charger UC-5 | G14: -5 | H14: 500
A15: 10107 | B15: 45296 | C15: Kisumu | D15: FAITH WANJIRU | E15: P001 | F15: 20L Jerrycan - Blue | G15: 4 | H15: 500
A16: 10067 | B16: 45346 | C16: thika | D16: Samuel Kiptoo | E16: P008 | F16: USB Wall Charger UC-5 | G16: 5 | H16: 500
A17: 10030 | B17: 45445 | C17: Mombasa | D17: Brian Mutua | E17: P013 | F17: Kitchen Knife Set | G17: 15 | H17: 1400
A18: 10109 | B18: 45597 | C18: thika | D18: Brian Mutua | E18: P002 | F18: Solar Lantern SL200 | G18: 8 | H18: 1550
A19: 10218 | B19: 45365 | C19: Thika | D19: Faith Wanjiru | E19: P003 | F19: RECHARGEABLE TORCH RT-10 | G19: 10 | H19: 900
A20: 10228 | B20: 45381 | C20: Thika | D20: Grace Achieng | E20: P014 | F20: LED Bulb 9W (Pack of 4) | G20: 4 | H20: 780
A21: 10111 | B21: 21/01/2024 | C21: Nairobi | D21: PETER OTIENO | E21: P014 | F21: LED Bulb 9W (Pack of 4) | G21: 15 | H21: 830
A22: 10255 | B22: 45446 | C22: Eldoret | D22: Faith Wanjiru | E22: P011 | F22: Padlock Set (3pc) | G22: 20 | H22: 750
A23: 10236 | B23: 45335 | C23: Thika | D23: Faith Wanjiru | E23: P011 | F23: PADLOCK SET (3PC) | G23: 12 | H23: 750
A24: 10055 | B24: 2024.03.27 | C24: Kisumu | D24: John Mwangi | E24: P013 | F24: Kitchen Knife Set | G24: 3 | H24: 1350
A25: 10090 | B25: 45335 | C25: Mombasa | D25: Mercy Njeri | E25: P013 | F25: Kitchen Knife Set | G25: 3 | H25: 1250
A26: 10197 | B26: 45338 | C26: NAKURU | D26: Peter Otieno | E26: P003 | F26: RECHARGEABLE TORCH RT-10 | G26: 1 | H26: 1050
A27: 10242 | B27: 45368 | D27: MERCY NJERI | E27: P007 | F27: MOSQUITO NET - FAMILY SIZE | G27: 20 | H27: 650
A28: 10289 | B28: 18/02/2024 | C28: Nakuru | D28: Peter Otieno | E28: P002 | F28: Solar Lantern SL-200 | G28: 1 | H28: 1450
A29: 10108 | B29: 2024.03.24 | C29: KISUMU | D29: Samuel Kiptoo | E29: P002 | F29: solar lantern sl-200 | G29: 6 | H29: 1500
A30: 10087 | B30: 45342 | D30: John Mwangi | E30: P001 | F30: 20L Jerrycan - Blue | G30: 4 | H30: 550
A31: 10263 | B31: 45328 | C31: Thika | D31: Samuel Kiptoo | E31: P003 | F31: Rechargeable Torch RT-10 | G31: 1 | H31: 950
A32: 10038 | B32: 45376 | C32: Nairobi | D32: Grace Achieng | E32: P011 | F32: Padlock Set (3pc) | G32: 8 | H32: 700
A33: 10148 | B33: 45299 | C33: Eldoret | D33: Brian Mutua | E33: P007 | F33: Mosquito Net - Family Size | G33: 12 | H33: 750
A34: 10180 | B34: 45382 | C34: Eldoret | D34: Brian Mutua | E34: P003 | F34: Rechargeable Torch RT-10 | G34: 15 | H34: 950
A35: 10027 | B35: 45296 | C35: Nairobi | D35: Brian Mutua | E35: P006 | F35: plastic storage basket l | G35: 6 | H35: 470
A36: 10276 | B36: 2024.01.19 | C36: Mombasa | D36: Peter Otieno | E36: P004 | F36: Cooking Gas Burner CB-2 | G36: 15 | H36: 1850
A37: 10184 | B37: 45308 | C37: ELDORET | D37: Aisha Hassan | E37: P013 | F37: Kitchen Knife Set | G37: 6 | H37: 1250
A38: 10062 | B38: 45375 | C38: Mombasa | D38: Aisha Hassan | E38: P001 | F38: 20L Jerrycan - Blue | G38: 3 | H38: 650
A39: 10296 | B39: 45375 | C39: ELDORET | D39: Samuel Kiptoo | E39: P012 | F39: Garden Hose 20m | G39: 15 | H39: 1650
A40: 10186 | B40: 2024.01.12 | C40: Thika | D40: Grace Achieng | E40: P001 | F40: 20L Jerrycan - Blue | G40: 4 | H40: 600
A41: 10311 | B41: 2024.02.10 | C41: Thika | D41: Samuel Kiptoo | E41: P012 | F41: Garden Hose 20m | G41: 5 | H41: 1800
A42: 10170 | B42: 45336 | C42: Nairobi | D42: AISHA HASSAN | E42: P002 | F42: solar lantern sl-200 | G42: 5 | H42: 1500
A43: 10044 | B43: 45367 | C43: Kisumu | D43: Mercy Njeri | E43: P014 | F43: LED Bulb 9W (Pack of 4) | G43: 4 | H43: 730
A44: 10213 | B44: 45333 | C44: Nairobi | D44: John Mwangi | E44: P003 | F44: RECHARGEABLE TORCH RT-10 | G44: 15 | H44: 950
A45: 10003 | B45: 45335 | C45: Nairobi | D45: Grace Achieng | E45: P007 | F45: Mosquito Net - Family Size | G45: 2 | H45: 650
A46: 10284 | B46: 45358 | C46: Thika | D46: samuel kiptoo | E46: P014 | F46: LED Bulb 9W (Pack of 4) | G46: 5 | H46: 880
A47: 10125 | B47: 18/01/2024 | C47: Thika | D47: Mercy Njeri | E47: P013 | F47: Kitchen Knife Set | G47: 10 | H47: 1400
A48: 10173 | B48: 45367 | C48: Nakuru | D48: Brian Mutua | E48: P001 | F48: 20L Jerrycan - Blue | G48: 4 | H48: 550
A49: 10312 | B49: 45294 | C49: Mombasa | D49: Faith Wanjiru | E49: P011 | F49: Padlock Set (3pc) | G49: 5 | H49: 650
A50: 10115 | B50: 45599 | C50: Mombasa | D50: grace achieng | E50: P002 | F50: SOLAR LANTERN SL-200 | G50: 5 | H50: 1500
A51: 10291 | B51: 45353 | C51: Nakuru | D51: Mercy Njeri | E51: P010 | F51: Wheelbarrow Heavy Duty | G51: 15 | H51: 5150
A52: 10234 | B52: 45376 | C52: kisumu | D52: Samuel Kiptoo | E52: P005 | F52: Non-Stick Frying Pan 28cm | G52: 20 | H52: 1050
A53: 10335 | B53: 45374 | C53: Kisumu | D53: John Mwangi | E53: P012 | F53: Garden Hose 20m | G53: 15 | H53: 1750
A54: 10041 | B54: 45312 | C54: Kisumu | D54: Grace Achieng | E54: P010 | F54: Wheelbarrow - Heavy Duty | G54: 1 | H54: 5200
A55: 10093 | B55: 45445 | C55: Nairobi | D55: Grace Achieng | E55: P010 | F55: Wheelbarrow - Heavy Duty | G55: 15 | H55: 5300
A56: 10018 | B56: 45446 | C56: Nairobi | D56: Peter Otieno | E56: P002 | F56: SOLAR LANTERN SL-200 | G56: 15 | H56: 1400
A57: 10209 | B57: 45337 | D57: Aisha Hassan | E57: P006 | F57: Plastic Storage Basket (L) | G57: 15 | H57: 520
A58: 10298 | B58: 45358 | C58: nairobi | D58: Grace Achieng | E58: P015 | F58: Water Dispenser Stand | G58: 2 | H58: 2400
A59: 10080 | B59: 45356 | C59: eldoret | D59: Brian Mutua | E59: P002 | F59: solar lantern sl-200 | G59: 2 | H59: 1550
A60: 10099 | B60: 2024.03.27 | C60: Thika | D60: Faith Wanjiru | E60: P008 | F60: USB Wall Charger UC-5 | G60: 15 | H60: 500
A61: 10012 | B61: 45319 | C61: Eldoret | D61: faith wanjiru | E61: P012 | F61: Garden Hose 20m | G61: 5 | H61: 1750
A62: 10246 | B62: 45312 | C62: Nairobi | D62: Aisha Hassan | E62: P015 | F62: WATER DISPENSER STAND | G62: 4
A63: 10097 | B63: 45374 | C63: kisumu | D63: Peter Otieno | E63: P011 | F63: Padlock Set (3pc) | G63: 20 | H63: 800
A64: 10337 | B64: 45303 | C64: Mombasa | D64: Brian Mutua | E64: P005 | F64: Non-Stick Frying Pan 28cm | G64: 8 | H64: 1100
A65: 10330 | B65: 45372 | C65: Mombasa | D65: Brian Mutua | E65: P012 | F65: Garden Hose 20m | G65: 2 | H65: 1800
A66: 10151 | B66: 45332 | C66: Mombasa | D66: Mercy Njeri | E66: P006 | F66: Plastic Storage Basket (L) | G66: 8 | H66: 370
A67: 10264 | B67: 45322 | C67: Eldoret | D67: Samuel Kiptoo | E67: P012 | F67: Garden Hose 20m | G67: 20 | H67: 1650
A68: 10280 | B68: 45353 | C68: Thika | D68: Grace Achieng | E68: P012 | F68: Garden Hose 20m | G68: 2 | H68: 1650
A69: 10108 | B69: 2024.03.24 | C69: KISUMU | D69: Samuel Kiptoo | E69: P002 | F69: solar lantern sl-200 | G69: 6 | H69: 1500
A70: 10072 | B70: 14/01/2024 | C70: Thika | D70: Faith Wanjiru | E70: P008 | F70: USB Wall Charger UC-5 | G70: 1 | H70: 600
A71: 10077 | B71: 45376 | C71: Nairobi | D71: Peter Otieno | E71: P001 | F71: 20L Jerrycan - Blue | G71: 6
A72: 10201 | B72: 19/01/2024 | C72: Thika | D72: SAMUEL KIPTOO | E72: P002 | F72: SOLAR LANTERN SL-200 | G72: 1 | H72: 1450
A73: 10204 | B73: 45379 | C73: Kisumu | D73: JOHN MWANGI | E73: P004 | F73: Cooking Gas Burner CB-2 | G73: 6 | H73: 1850
A74: 10176 | B74: 45373 | C74: Eldoret | D74: Peter Otieno | E74: P009 | F74: Thermos Flask 1L | G74: 3 | H74: 950
A75: 10059 | B75: 45329 | C75: Eldoret | D75: Samuel Kiptoo | E75: P007 | F75: Mosquito Net - Family Size | G75: 10 | H75: 700
A76: 10002 | B76: 45295 | C76: Eldoret | D76: Faith Wanjiru | E76: P012 | F76: Garden Hose 20m | G76: 20 | H76: 1800
A77: 10189 | B77: 14/02/2024 | C77: Nakuru | D77: Mercy Njeri | E77: P013 | F77: Kitchen Knife Set | G77: 3 | H77: 1300
A78: 10001 | B78: 45373 | C78: Nairobi | D78: John Mwangi | E78: P012 | F78: Garden Hose 20m | G78: 5 | H78: 1700
A79: 10026 | B79: 45327 | C79: Nairobi | D79: Samuel Kiptoo | E79: P006 | F79: Plastic Storage Basket (L) | G79: 20 | H79: 520
A80: 10281 | B80: 45352 | C80: Thika | D80: Peter Otieno | E80: P006 | F80: Plastic Storage Basket L | G80: 8 | H80: 420
A81: 10145 | B81: 45444 | C81: Nakuru | D81: Aisha Hassan | E81: P004 | F81: Cooking Gas Burner CB-2 | G81: 12 | H81: 1850
A82: 10141 | B82: 45294 | C82: Nakuru | D82: Samuel Kiptoo | E82: P014 | F82: LED Bulb 9W (Pack of 4) | G82: 1 | H82: 780
A83: 10179 | B83: 45346 | C83: Nairobi | D83: Faith Wanjiru | E83: P005 | F83: Non-Stick Frying Pan 28cm | G83: 1 | H83: 1150
A84: 10295 | B84: 45474 | C84: mombasa | D84: Brian Mutua | E84: P011 | F84: Padlock Set (3pc) | G84: 1 | H84: 650
A85: 10112 | B85: 45301 | C85: ELDORET | D85: Peter Otieno | E85: P009 | F85: Thermos Flask 1L | G85: 6 | H85: 950
A86: 10086 | B86: 45302 | C86: Kisumu | D86: Aisha Hassan | E86: P011 | F86: Padlock Set (3pc) | G86: 8 | H86: 750
A87: 10040 | B87: 20/01/2024 | C87: Mombasa | D87: Peter Otieno | E87: P008 | F87: USB WALL CHARGER UC-5 | G87: 20 | H87: 450
A88: 10054 | B88: 45326 | C88: Eldoret | D88: Aisha Hassan | E88: P008 | F88: USB Wall Charger UC-5 | G88: 2 | H88: 600
A89: 10133 | B89: 2024.02.22 | C89: Thika | D89: Aisha Hassan | E89: P008 | F89: USB Wall Charger UC-5 | G89: 20 | H89: 500
A90: 10105 | B90: 16/02/2024 | C90: Nairobi | D90: John Mwangi | E90: P007 | F90: Mosquito Net - Family Size | G90: 10 | H90: 600
A91: 10019 | B91: 45376 | C91: Eldoret | D91: Mercy Njeri | E91: P015 | F91: Water Dispenser Stand | G91: 5 | H91: 2300
A92: 10136 | B92: 2024.03.27 | C92: Mombasa | D92: peter otieno | E92: P010 | F92: Wheelbarrow - Heavy Duty | G92: 20 | H92: 5250
A93: 10020 | B93: 45304 | C93: NAIROBI | D93: Faith Wanjiru | E93: P009 | F93: Thermos Flask 1L | G93: 5 | H93: 900
A94: 10085 | B94: 45359 | C94: Mombasa | D94: Brian Mutua | E94: P007 | F94: Mosquito Net - Family Size | G94: 10 | H94: 650
A95: 10073 | B95: 45444 | C95: Nairobi | D95: Samuel Kiptoo | E95: P008 | F95: USB Wall Charger UC-5 | G95: 2 | H95: 450
A96: 10149 | B96: 45326 | C96: NAKURU | D96: John Mwangi | E96: P014 | F96: LED Bulb 9W (Pack of 4) | G96: 2 | H96: 780
A97: 10022 | B97: 45353 | C97: ELDORET | D97: Aisha Hassan | E97: P005 | F97: Non-Stick Frying Pan 28cm | G97: 1 | H97: 1050
A98: 10006 | B98: 45299 | C98: Mombasa | D98: John Mwangi | E98: P013 | F98: Kitchen Knife Set | G98: 6 | H98: 1350
A99: 10314 | B99: 45361 | C99: Kisumu | D99: Aisha Hassan | E99: P003 | F99: Rechargeable Torch RT-10 | G99: 12 | H99: 950
A100: 10247 | B100: 45357 | C100: NAIROBI | D100: Grace Achieng | E100: P015 | F100: Water Dispenser Stand | G100: 5 | H100: 2300
...

Sheet Cleaned Sales Data
A1: Order ID | B1: Order Date | C1: Cleaned Order Date | D1: Region | E1: Cleaned Region | F1: Sales Rep | G1: Cleaned Sales Rep | H1: Product ID | I1: Product Name | J1: Cleaned Product Name | K1: Quantity | L1: New Quantity | M1: Unit Price (KES) | N1: Cleaned Unit Price (KES) | O1: Flags | P1: Cleaned Quantity | Q1: Unit Cost | R1: Category | S1: Revenue | T1: Cost | U1: Profit | V1: Margin % | W1: Month
A2: 10008 | B2: 45306 | C2: 45306 | D2: mombasa | E2: =PROPER(TRIM(D2)) -> Mombasa | F2: Peter Otieno | G2: =PROPER(TRIM(F2)) -> Peter Otieno | H2: P013 | I2: Kitchen Knife Set | J2: =PROPER(TRIM(I2)) -> Kitchen Knife Set | K2: 20 | L2: =IF(K2="",0,K2) -> 20 | M2: 1350 | N2: =IF(M2="",0,M2) -> 1350 | O2: =IF(L2<0,"NEGATIVE QUANTITY","") | P2: =ABS(L2) -> 20 | Q2: =VLOOKUP(H2,'Product Cost Lookup'!A:D,4,FALSE) -> 800 | R2: =VLOOKUP(H2,'Product Cost Lookup'!A:D,3,FALSE) -> Kitchenware | S2: =P2*N2 -> 27000 | T2: =P2*Q2 -> 16000 | U2: =S2-T2 -> 11000 | V2: =IF(S2=0,0,U2/S2) -> 0.40740741 | W2: =TEXT(C2,"mmm") -> Jan
A3: 10300 | B3: 45364 | C3: 45364 | D3: nakuru | E3: =PROPER(TRIM(D3)) -> Nakuru | F3: Faith Wanjiru | G3: =PROPER(TRIM(F3)) -> Faith Wanjiru | H3: P013 | I3: Kitchen Knife Set | J3: =PROPER(TRIM(I3)) -> Kitchen Knife Set | K3: 6 | L3: =IF(K3="",0,K3) -> 6 | M3: 1350 | N3: =IF(M3="",0,M3) -> 1350 | O3: =IF(L3<0,"NEGATIVE QUANTITY","") | P3: =ABS(L3) -> 6 | Q3: =VLOOKUP(H3,'Product Cost Lookup'!A:D,4,FALSE) -> 800 | R3: =VLOOKUP(H3,'Product Cost Lookup'!A:D,3,FALSE) -> Kitchenware | S3: =P3*N3 -> 8100 | T3: =P3*Q3 -> 4800 | U3: =S3-T3 -> 3300 | V3: =IF(S3=0,0,U3/S3) -> 0.40740741 | W3: =TEXT(C3,"mmm") -> Mar
A4: 10328 | B4: 45338 | C4: 45338 | D4: Mombasa | E4: =PROPER(TRIM(D4)) -> Mombasa | F4: Grace Achieng | G4: =PROPER(TRIM(F4)) -> Grace Achieng | H4: P001 | I4: 20L Jerrycan - Blue | J4: =PROPER(TRIM(I4)) -> 20L Jerrycan - Blue | K4: 4 | L4: =IF(K4="",0,K4) -> 4 | M4: 600 | N4: =IF(M4="",0,M4) -> 600 | O4: =IF(L4<0,"NEGATIVE QUANTITY","") | P4: =ABS(L4) -> 4 | Q4: =VLOOKUP(H4,'Product Cost Lookup'!A:D,4,FALSE) -> 350 | R4: =VLOOKUP(H4,'Product Cost Lookup'!A:D,3,FALSE) -> Household | S4: =P4*N4 -> 2400 | T4: =P4*Q4 -> 1400 | U4: =S4-T4 -> 1000 | V4: =IF(S4=0,0,U4/S4) -> 0.41666667 | W4: =TEXT(C4,"mmm") -> Feb
A5: 10216 | B5: 45373 | C5: 45373 | D5: Eldoret | E5: =PROPER(TRIM(D5)) -> Eldoret | F5: grace achieng | G5: =PROPER(TRIM(F5)) -> Grace Achieng | H5: P015 | I5: Water Dispenser Stand | J5: =PROPER(TRIM(I5)) -> Water Dispenser Stand | K5: 10 | L5: =IF(K5="",0,K5) -> 10 | M5: 2300 | N5: =IF(M5="",0,M5) -> 2300 | O5: =IF(L5<0,"NEGATIVE QUANTITY","") | P5: =ABS(L5) -> 10 | Q5: =VLOOKUP(H5,'Product Cost Lookup'!A:D,4,FALSE) -> 1500 | R5: =VLOOKUP(H5,'Product Cost Lookup'!A:D,3,FALSE) -> Household | S5: =P5*N5 -> 23000 | T5: =P5*Q5 -> 15000 | U5: =S5-T5 -> 8000 | V5: =IF(S5=0,0,U5/S5) -> 0.34782609 | W5: =TEXT(C5,"mmm") -> Mar
A6: 10065 | B6: 45505 | C6: 45505 | D6: KISUMU | E6: =PROPER(TRIM(D6)) -> Kisumu | F6: Mercy Njeri | G6: =PROPER(TRIM(F6)) -> Mercy Njeri | H6: P006 | I6: Plastic Storage Basket L | J6: =PROPER(TRIM(I6)) -> Plastic Storage Basket L | K6: 8 | L6: =IF(K6="",0,K6) -> 8 | M6: 420 | N6: =IF(M6="",0,M6) -> 420 | O6: =IF(L6<0,"NEGATIVE QUANTITY","") | P6: =ABS(L6) -> 8 | Q6: =VLOOKUP(H6,'Product Cost Lookup'!A:D,4,FALSE) -> 250 | R6: =VLOOKUP(H6,'Product Cost Lookup'!A:D,3,FALSE) -> Household | S6: =P6*N6 -> 3360 | T6: =P6*Q6 -> 2000 | U6: =S6-T6 -> 1360 | V6: =IF(S6=0,0,U6/S6) -> 0.4047619 | W6: =TEXT(C6,"mmm") -> Aug
A7: 10222 | B7: 45339 | C7: 45339 | D7: Mombasa | E7: =PROPER(TRIM(D7)) -> Mombasa | F7: aisha hassan | G7: =PROPER(TRIM(F7)) -> Aisha Hassan | H7: P001 | I7: 20L Jerrycan - Blue | J7: =PROPER(TRIM(I7)) -> 20L Jerrycan - Blue | K7: 5 | L7: =IF(K7="",0,K7) -> 5 | M7: 600 | N7: =IF(M7="",0,M7) -> 600 | O7: =IF(L7<0,"NEGATIVE QUANTITY","") | P7: =ABS(L7) -> 5 | Q7: =VLOOKUP(H7,'Product Cost Lookup'!A:D,4,FALSE) -> 350 | R7: =VLOOKUP(H7,'Product Cost Lookup'!A:D,3,FALSE) -> Household | S7: =P7*N7 -> 3000 | T7: =P7*Q7 -> 1750 | U7: =S7-T7 -> 1250 | V7: =IF(S7=0,0,U7/S7) -> 0.41666667 | W7: =TEXT(C7,"mmm") -> Feb
A8: 10140 | B8: 45306 | C8: 45306 | D8: Thika | E8: =PROPER(TRIM(D8)) -> Thika | F8: Faith Wanjiru | G8: =PROPER(TRIM(F8)) -> Faith Wanjiru | H8: P012 | I8: Garden Hose 20m | J8: =PROPER(TRIM(I8)) -> Garden Hose 20M | K8: 15 | L8: =IF(K8="",0,K8) -> 15 | M8: 1750 | N8: =IF(M8="",0,M8) -> 1750 | O8: =IF(L8<0,"NEGATIVE QUANTITY","") | P8: =ABS(L8) -> 15 | Q8: =VLOOKUP(H8,'Product Cost Lookup'!A:D,4,FALSE) -> 1100 | R8: =VLOOKUP(H8,'Product Cost Lookup'!A:D,3,FALSE) -> Hardware | S8: =P8*N8 -> 26250 | T8: =P8*Q8 -> 16500 | U8: =S8-T8 -> 9750 | V8: =IF(S8=0,0,U8/S8) -> 0.37142857 | W8: =TEXT(C8,"mmm") -> Jan
A9: 10268 | B9: 45336 | C9: 45336 | D9: Mombasa | E9: =PROPER(TRIM(D9)) -> Mombasa | F9: Faith Wanjiru | G9: =PROPER(TRIM(F9)) -> Faith Wanjiru | H9: P011 | I9: PADLOCK SET (3PC) | J9: =PROPER(TRIM(I9)) -> Padlock Set (3Pc) | K9: 6 | L9: =IF(K9="",0,K9) -> 6 | M9: 700 | N9: =IF(M9="",0,M9) -> 700 | O9: =IF(L9<0,"NEGATIVE QUANTITY","") | P9: =ABS(L9) -> 6 | Q9: =VLOOKUP(H9,'Product Cost Lookup'!A:D,4,FALSE) -> 450 | R9: =VLOOKUP(H9,'Product Cost Lookup'!A:D,3,FALSE) -> Hardware | S9: =P9*N9 -> 4200 | T9: =P9*Q9 -> 2700 | U9: =S9-T9 -> 1500 | V9: =IF(S9=0,0,U9/S9) -> 0.35714286 | W9: =TEXT(C9,"mmm") -> Feb
A10: 10025 | B10: 45323 | C10: 45323 | D10: Kisumu | E10: =PROPER(TRIM(D10)) -> Kisumu | F10: PETER OTIENO | G10: =PROPER(TRIM(F10)) -> Peter Otieno | H10: P013 | I10: Kitchen Knife Set | J10: =PROPER(TRIM(I10)) -> Kitchen Knife Set | K10: 2 | L10: =IF(K10="",0,K10) -> 2 | M10: 1350 | N10: =IF(M10="",0,M10) -> 1350 | O10: =IF(L10<0,"NEGATIVE QUANTITY","") | P10: =ABS(L10) -> 2 | Q10: =VLOOKUP(H10,'Product Cost Lookup'!A:D,4,FALSE) -> 800 | R10: =VLOOKUP(H10,'Product Cost Lookup'!A:D,3,FALSE) -> Kitchenware | S10: =P10*N10 -> 2700 | T10: =P10*Q10 -> 1600 | U10: =S10-T10 -> 1100 | V10: =IF(S10=0,0,U10/S10) -> 0.40740741 | W10: =TEXT(C10,"mmm") -> Feb
A11: 10205 | B11: 45599 | C11: 45599 | D11: MOMBASA | E11: =PROPER(TRIM(D11)) -> Mombasa | F11: Grace Achieng | G11: =PROPER(TRIM(F11)) -> Grace Achieng | H11: P008 | I11: USB Wall Charger UC-5 | J11: =PROPER(TRIM(I11)) -> Usb Wall Charger Uc-5 | K11: 2 | L11: =IF(K11="",0,K11) -> 2 | M11: 500 | N11: =IF(M11="",0,M11) -> 500 | O11: =IF(L11<0,"NEGATIVE QUANTITY","") | P11: =ABS(L11) -> 2 | Q11: =VLOOKUP(H11,'Product Cost Lookup'!A:D,4,FALSE) -> 300 | R11: =VLOOKUP(H11,'Product Cost Lookup'!A:D,3,FALSE) -> Electronics | S11: =P11*N11 -> 1000 | T11: =P11*Q11 -> 600 | U11: =S11-T11 -> 400 | V11: =IF(S11=0,0,U11/S11) -> 0.4 | W11: =TEXT(C11,"mmm") -> Nov
A12: 10188 | B12: 45370 | C12: 45370 | D12: Thika | E12: =PROPER(TRIM(D12)) -> Thika | F12: Peter Otieno | G12: =PROPER(TRIM(F12)) -> Peter Otieno | H12: P008 | I12: USB Wall Charger UC-5 | J12: =PROPER(TRIM(I12)) -> Usb Wall Charger Uc-5 | K12: 6 | L12: =IF(K12="",0,K12) -> 6 | M12: 500 | N12: =IF(M12="",0,M12) -> 500 | O12: =IF(L12<0,"NEGATIVE QUANTITY","") | P12: =ABS(L12) -> 6 | Q12: =VLOOKUP(H12,'Product Cost Lookup'!A:D,4,FALSE) -> 300 | R12: =VLOOKUP(H12,'Product Cost Lookup'!A:D,3,FALSE) -> Electronics | S12: =P12*N12 -> 3000 | T12: =P12*Q12 -> 1800 | U12: =S12-T12 -> 1200 | V12: =IF(S12=0,0,U12/S12) -> 0.4 | W12: =TEXT(C12,"mmm") -> Mar
A13: 10152 | B13: 45321 | C13: 45321 | D13: Nakuru | E13: =PROPER(TRIM(D13)) -> Nakuru | F13: faith wanjiru | G13: =PROPER(TRIM(F13)) -> Faith Wanjiru | H13: P008 | I13: USB Wall Charger UC-5 | J13: =PROPER(TRIM(I13)) -> Usb Wall Charger Uc-5 | K13: 12 | L13: =IF(K13="",0,K13) -> 12 | M13: 500 | N13: =IF(M13="",0,M13) -> 500 | O13: =IF(L13<0,"NEGATIVE QUANTITY","") | P13: =ABS(L13) -> 12 | Q13: =VLOOKUP(H13,'Product Cost Lookup'!A:D,4,FALSE) -> 300 | R13: =VLOOKUP(H13,'Product Cost Lookup'!A:D,3,FALSE) -> Electronics | S13: =P13*N13 -> 6000 | T13: =P13*Q13 -> 3600 | U13: =S13-T13 -> 2400 | V13: =IF(S13=0,0,U13/S13) -> 0.4 | W13: =TEXT(C13,"mmm") -> Jan
... A20: 10228 | B20: 45381 | C20: 45381 | D20: Thika | E20: =PROPER(TRIM(D20)) -> Thika | F20: Grace Achieng | G20: =PROPER(TRIM(F20)) -> Grace Achieng | H20: P014 | I20: LED Bulb 9W (Pack of 4) | J20: =PROPER(TRIM(I20)) -> Led Bulb 9W (Pack Of 4) | K20: 4 | L20: =IF(K20="",0,K20) -> 4 | M20: 780 | N20: =IF(M20="",0,M20) -> 780 | O20: =IF(L20<0,"NEGATIVE QUANTITY","") | P20: =ABS(L20) -> 4 | Q20: =VLOOKUP(H20,'Product Cost Lookup'!A:D,4,FALSE) -> 480 | R20: =VLOOKUP(H20,'Product Cost Lookup'!A:D,3,FALSE) -> Electronics | S20: =P20*N20 -> 3120 | T20: =P20*Q20 -> 1920 | U20: =S20-T20 -> 1200 | V20: =IF(S20=0,0,U20/S20) -> 0.38461538 | W20: =TEXT(C20,"mmm") -> Mar
A21: 10111 | B21: 21/01/2024 | C21: 45312 | D21: Nairobi | E21: =PROPER(TRIM(D21)) -> Nairobi | F21: PETER OTIENO | G21: =PROPER(TRIM(F21)) -> Peter Otieno | H21: P014 | I21: LED Bulb 9W (Pack of 4) | J21: =PROPER(TRIM(I21)) -> Led Bulb 9W (Pack Of 4) | K21: 15 | L21: =IF(K21="",0,K21) -> 15 | M21: 830 | N21: =IF(M21="",0,M21) -> 830 | O21: =IF(L21<0,"NEGATIVE QUANTITY","") | P21: =ABS(L21) -> 15 | Q21: =VLOOKUP(H21,'Product Cost Lookup'!A:D,4,FALSE) -> 480 | R21: =VLOOKUP(H21,'Product Cost Lookup'!A:D,3,FALSE) -> Electronics | S21: =P21*N21 -> 12450 | T21: =P21*Q21 -> 7200 | U21: =S21-T21 -> 5250 | V21: =IF(S21=0,0,U21/S21) -> 0.42168675 | W21: =TEXT(C21,"mmm") -> Jan
A22: 10255 | B22: 45446 | C22: 45446 | D22: Eldoret | E22: =PROPER(TRIM(D22)) -> Eldoret | F22: Faith Wanjiru | G22: =PROPER(TRIM(F22)) -> Faith Wanjiru | H22: P011 | I22: Padlock Set (3pc) | J22: =PROPER(TRIM(I22)) -> Padlock Set (3Pc) | K22: 20 | L22: =IF(K22="",0,K22) -> 20 | M22: 750 | N22: =IF(M22="",0,M22) -> 750 | O22: =IF(L22<0,"NEGATIVE QUANTITY","") | P22: =ABS(L22) -> 20 | Q22: =VLOOKUP(H22,'Product Cost Lookup'!A:D,4,FALSE) -> 450 | R22: =VLOOKUP(H22,'Product Cost Lookup'!A:D,3,FALSE) -> Hardware | S22: =P22*N22 -> 15000 | T22: =P22*Q22 -> 9000 | U22: =S22-T22 -> 6000 | V22: =IF(S22=0,0,U22/S22) -> 0.4 | W22: =TEXT(C22,"mmm") -> Jun
A23: 10236 | B23: 45335 | C23: 45335 | D23: Thika | E23: =PROPER(TRIM(D23)) -> Thika | F23: Faith Wanjiru | G23: =PROPER(TRIM(F23)) -> Faith Wanjiru | H23: P011 | I23: PADLOCK SET (3PC) | J23: =PROPER(TRIM(I23)) -> Padlock Set (3Pc) | K23: 12 | L23: =IF(K23="",0,K23) -> 12 | M23: 750 | N23: =IF(M23="",0,M23) -> 750 | O23: =IF(L23<0,"NEGATIVE QUANTITY","") | P23: =ABS(L23) -> 12 | Q23: =VLOOKUP(H23,'Product Cost Lookup'!A:D,4,FALSE) -> 450 | R23: =VLOOKUP(H23,'Product Cost Lookup'!A:D,3,FALSE) -> Hardware | S23: =P23*N23 -> 9000 | T23: =P23*Q23 -> 5400 | U23: =S23-T23 -> 3600 | V23: =IF(S23=0,0,U23/S23) -> 0.4 | W23: =TEXT(C23,"mmm") -> Feb
A24: 10055 | B24: 45378 | C24: 45378 | D24: Kisumu | E24: =PROPER(TRIM(D24)) -> Kisumu | F24: John Mwangi | G24: =PROPER(TRIM(F24)) -> John Mwangi | H24: P013 | I24: Kitchen Knife Set | J24: =PROPER(TRIM(I24)) -> Kitchen Knife Set | K24: 3 | L24: =IF(K24="",0,K24) -> 3 | M24: 1350 | N24: =IF(M24="",0,M24) -> 1350 | O24: =IF(L24<0,"NEGATIVE QUANTITY","") | P24: =ABS(L24) -> 3 | Q24: =VLOOKUP(H24,'Product Cost Lookup'!A:D,4,FALSE) -> 800 | R24: =VLOOKUP(H24,'Product Cost Lookup'!A:D,3,FALSE) -> Kitchenware | S24: =P24*N24 -> 4050 | T24: =P24*Q24 -> 2400 | U24: =S24-T24 -> 1650 | V24: =IF(S24=0,0,U24/S24) -> 0.40740741 | W24: =TEXT(C24,"mmm") -> Mar
A25: 10090 | B25: 45335 | C25: 45335 | D25: Mombasa | E25: =PROPER(TRIM(D25)) -> Mombasa | F25: Mercy Njeri | G25: =PROPER(TRIM(F25)) -> Mercy Njeri | H25: P013 | I25: Kitchen Knife Set | J25: =PROPER(TRIM(I25)) -> Kitchen Knife Set | K25: 3 | L25: =IF(K25="",0,K25) -> 3 | M25: 1250 | N25: =IF(M25="",0,M25) -> 1250 | O25: =IF(L25<0,"NEGATIVE QUANTITY","") | P25: =ABS(L25) -> 3 | Q25: =VLOOKUP(H25,'Product Cost Lookup'!A:D,4,FALSE) -> 800 | R25: =VLOOKUP(H25,'Product Cost Lookup'!A:D,3,FALSE) -> Kitchenware | S25: =P25*N25 -> 3750 | T25: =P25*Q25 -> 2400 | U25: =S25-T25 -> 1350 | V25: =IF(S25=0,0,U25/S25) -> 0.36 | W25: =TEXT(C25,"mmm") -> Feb
A26: 10197 | B26: 45338 | C26: 45338 | D26: NAKURU | E26: =PROPER(TRIM(D26)) -> Nakuru | F26: Peter Otieno | G26: =PROPER(TRIM(F26)) -> Peter Otieno | H26: P003 | I26: RECHARGEABLE TORCH RT-10 | J26: =PROPER(TRIM(I26)) -> Rechargeable Torch Rt-10 | K26: 1 | L26: =IF(K26="",0,K26) -> 1 | M26: 1050 | N26: =IF(M26="",0,M26) -> 1050 | O26: =IF(L26<0,"NEGATIVE QUANTITY","") | P26: =ABS(L26) -> 1 | Q26: =VLOOKUP(H26,'Product Cost Lookup'!A:D,4,FALSE) -> 600 | R26: =VLOOKUP(H26,'Product Cost Lookup'!A:D,3,FALSE) -> Electronics | S26: =P26*N26 -> 1050 | T26: =P26*Q26 -> 600 | U26: =S26-T26 -> 450 | V26: =IF(S26=0,0,U26/S26) -> 0.42857143 | W26: =TEXT(C26,"mmm") -> Feb
A27: 10242 | B27: 45368 | C27: 45368 | E27: =IF(TRIM(D27)="","Unknown",PROPER(TRIM(D27))) -> Unknown | F27: MERCY NJERI | G27: =PROPER(TRIM(F27)) -> Mercy Njeri | H27: P007 | I27: MOSQUITO NET - FAMILY SIZE | J27: =PROPER(TRIM(I27)) -> Mosquito Net - Family Size | K27: 20 | L27: =IF(K27="",0,K27) -> 20 | M27: 650 | N27: =IF(M27="",0,M27) -> 650 | O27: =IF(L27<0,"NEGATIVE QUANTITY","") | P27: =ABS(L27) -> 20 | Q27: =VLOOKUP(H27,'Product Cost Lookup'!A:D,4,FALSE) -> 400 | R27: =VLOOKUP(H27,'Product Cost Lookup'!A:D,3,FALSE) -> Household | S27: =P27*N27 -> 13000 | T27: =P27*Q27 -> 8000 | U27: =S27-T27 -> 5000 | V27: =IF(S27=0,0,U27/S27) -> 0.38461538 | W27: =TEXT(C27,"mmm") -> Mar
A28: 10289 | B28: 18/02/2024 | C28: 45340 | D28: Nakuru | E28: =IF(TRIM(D28)="","Unknown",PROPER(TRIM(D28))) -> Nakuru | F28: Peter Otieno | G28: =PROPER(TRIM(F28)) -> Peter Otieno | H28: P002 | I28: Solar Lantern SL-200 | J28: =PROPER(TRIM(I28)) -> Solar Lantern Sl-200 | K28: 1 | L28: =IF(K28="",0,K28) -> 1 | M28: 1450 | N28: =IF(M28="",0,M28) -> 1450 | O28: =IF(L28<0,"NEGATIVE QUANTITY","") | P28: =ABS(L28) -> 1 | Q28: =VLOOKUP(H28,'Product Cost Lookup'!A:D,4,FALSE) -> 900 | R28: =VLOOKUP(H28,'Product Cost Lookup'!A:D,3,FALSE) -> Electronics | S28: =P28*N28 -> 1450 | T28: =P28*Q28 -> 900 | U28: =S28-T28 -> 550 | V28: =IF(S28=0,0,U28/S28) -> 0.37931034 | W28: =TEXT(C28,"mmm") -> Feb
A29: 10108 | B29: 45375 | C29: 45375 | D29: KISUMU | E29: =IF(TRIM(D29)="","Unknown",PROPER(TRIM(D29))) -> Kisumu | F29: Samuel Kiptoo | G29: =PROPER(TRIM(F29)) -> Samuel Kiptoo | H29: P002 | I29: solar lantern sl-200 | J29: =PROPER(TRIM(I29)) -> Solar Lantern Sl-200 | K29: 6 | L29: =IF(K29="",0,K29) -> 6 | M29: 1500 | N29: =IF(M29="",0,M29) -> 1500 | O29: =IF(L29<0,"NEGATIVE QUANTITY","") | P29: =ABS(L29) -> 6 | Q29: =VLOOKUP(H29,'Product Cost Lookup'!A:D,4,FALSE) -> 900 | R29: =VLOOKUP(H29,'Product Cost Lookup'!A:D,3,FALSE) -> Electronics | S29: =P29*N29 -> 9000 | T29: =P29*Q29 -> 5400 | U29: =S29-T29 -> 3600 | V29: =IF(S29=0,0,U29/S29) -> 0.4 | W29: =TEXT(C29,"mmm") -> Mar
A30: 10087 | B30: 45342 | C30: 45342 | E30: =IF(TRIM(D30)="","Unknown",PROPER(TRIM(D30))) -> Unknown | F30: John Mwangi | G30: =PROPER(TRIM(F30)) -> John Mwangi | H30: P001 | I30: 20L Jerrycan - Blue | J30: =PROPER(TRIM(I30)) -> 20L Jerrycan - Blue | K30: 4 | L30: =IF(K30="",0,K30) -> 4 | M30: 550 | N30: =IF(M30="",0,M30) -> 550 | O30: =IF(L30<0,"NEGATIVE QUANTITY","") | P30: =ABS(L30) -> 4 | Q30: =VLOOKUP(H30,'Product Cost Lookup'!A:D,4,FALSE) -> 350 | R30: =VLOOKUP(H30,'Product Cost Lookup'!A:D,3,FALSE) -> Household | S30: =P30*N30 -> 2200 | T30: =P30*Q30 -> 1400 | U30: =S30-T30 -> 800 | V30: =IF(S30=0,0,U30/S30) -> 0.36363636 | W30: =TEXT(C30,"mmm") -> Feb
A31: 10263 | B31: 45328 | C31: 45328 | D31: Thika | E31: =IF(TRIM(D31)="","Unknown",PROPER(TRIM(D31))) -> Thika | F31: Samuel Kiptoo | G31: =PROPER(TRIM(F31)) -> Samuel Kiptoo | H31: P003 | I31: Rechargeable Torch RT-10 | J31: =PROPER(TRIM(I31)) -> Rechargeable Torch Rt-10 | K31: 1 | L31: =IF(K31="",0,K31) -> 1 | M31: 950 | N31: =IF(M31="",0,M31) -> 950 | O31: =IF(L31<0,"NEGATIVE QUANTITY","") | P31: =ABS(L31) -> 1 | Q31: =VLOOKUP(H31,'Product Cost Lookup'!A:D,4,FALSE) -> 600 | R31: =VLOOKUP(H31,'Product Cost Lookup'!A:D,3,FALSE) -> Electronics | S31: =P31*N31 -> 950 | T31: =P31*Q31 -> 600 | U31: =S31-T31 -> 350 | V31: =IF(S31=0,0,U31/S31) -> 0.36842105 | W31: =TEXT(C31,"mmm") -> Feb
A32: 10038 | B32: 45376 | C32: 45376 | D32: Nairobi | E32: =IF(TRIM(D32)="","Unknown",PROPER(TRIM(D32))) -> Nairobi | F32: Grace Achieng | G32: =PROPER(TRIM(F32)) -> Grace Achieng | H32: P011 | I32: Padlock Set (3pc) | J32: =PROPER(TRIM(I32)) -> Padlock Set (3Pc) | K32: 8 | L32: =IF(K32="",0,K32) -> 8 | M32: 700 | N32: =IF(M32="",0,M32) -> 700 | O32: =IF(L32<0,"NEGATIVE QUANTITY","") | P32: =ABS(L32) -> 8 | Q32: =VLOOKUP(H32,'Product Cost Lookup'!A:D,4,FALSE) -> 450 | R32: =VLOOKUP(H32,'Product Cost Lookup'!A:D,3,FALSE) -> Hardware | S32: =P32*N32 -> 5600 | T32: =P32*Q32 -> 3600 | U32: =S32-T32 -> 2000 | V32: =IF(S32=0,0,U32/S32) -> 0.35714286 | W32: =TEXT(C32,"mmm") -> Mar
A33: 10148 | B33: 45299 | C33: 45299 | D33: Eldoret | E33: =IF(TRIM(D33)="","Unknown",PROPER(TRIM(D33))) -> Eldoret | F33: Brian Mutua | G33: =PROPER(TRIM(F33)) -> Brian Mutua | H33: P007 | I33: Mosquito Net - Family Size | J33: =PROPER(TRIM(I33)) -> Mosquito Net - Family Size | K33: 12 | L33: =IF(K33="",0,K33) -> 12 | M33: 750 | N33: =IF(M33="",0,M33) -> 750 | O33: =IF(L33<0,"NEGATIVE QUANTITY","") | P33: =ABS(L33) -> 12 | Q33: =VLOOKUP(H33,'Product Cost Lookup'!A:D,4,FALSE) -> 400 | R33: =VLOOKUP(H33,'Product Cost Lookup'!A:D,3,FALSE) -> Household | S33: =P33*N33 -> 9000 | T33: =P33*Q33 -> 4800 | U33: =S33-T33 -> 4200 | V33: =IF(S33=0,0,U33/S33) -> 0.46666667 | W33: =TEXT(C33,"mmm") -> Jan
A34: 10180 | B34: 45382 | C34: 45382 | D34: Eldoret | E34: =IF(TRIM(D34)="","Unknown",PROPER(TRIM(D34))) -> Eldoret | F34: Brian Mutua | G34: =PROPER(TRIM(F34)) -> Brian Mutua | H34: P003 | I34: Rechargeable Torch RT-10 | J34: =PROPER(TRIM(I34)) -> Rechargeable Torch Rt-10 | K34: 15 | L34: =IF(K34="",0,K34) -> 15 | M34: 950 | N34: =IF(M34="",0,M34) -> 950 | O34: =IF(L34<0,"NEGATIVE QUANTITY","") | P34: =ABS(L34) -> 15 | Q34: =VLOOKUP(H34,'Product Cost Lookup'!A:D,4,FALSE) -> 600 | R34: =VLOOKUP(H34,'Product Cost Lookup'!A:D,3,FALSE) -> Electronics | S34: =P34*N34 -> 14250 | T34: =P34*Q34 -> 9000 | U34: =S34-T34 -> 5250 | V34: =IF(S34=0,0,U34/S34) -> 0.36842105 | W34: =TEXT(C34,"mmm") -> Mar
A35: 10027 | B35: 45296 | C35: 45296 | D35: Nairobi | E35: =IF(TRIM(D35)="","Unknown",PROPER(TRIM(D35))) -> Nairobi | F35: Brian Mutua | G35: =PROPER(TRIM(F35)) -> Brian Mutua | H35: P006 | I35: plastic storage basket l | J35: =PROPER(TRIM(I35)) -> Plastic Storage Basket L | K35: 6 | L35: =IF(K35="",0,K35) -> 6 | M35: 470 | N35: =IF(M35="",0,M35) -> 470 | O35: =IF(L35<0,"NEGATIVE QUANTITY","") | P35: =ABS(L35) -> 6 | Q35: =VLOOKUP(H35,'Product Cost Lookup'!A:D,4,FALSE) -> 250 | R35: =VLOOKUP(H35,'Product Cost Lookup'!A:D,3,FALSE) -> Household | S35: =P35*N35 -> 2820 | T35: =P35*Q35 -> 1500 | U35: =S35-T35 -> 1320 | V35: =IF(S35=0,0,U35/S35) -> 0.46808511 | W35: =TEXT(C35,"mmm") -> Jan
A36: 10276 | B36: 45310 | C36: 45310 | D36: Mombasa | E36: =IF(TRIM(D36)="","Unknown",PROPER(TRIM(D36))) -> Mombasa | F36: Peter Otieno | G36: =PROPER(TRIM(F36)) -> Peter Otieno | H36: P004 | I36: Cooking Gas Burner CB-2 | J36: =PROPER(TRIM(I36)) -> Cooking Gas Burner Cb-2 | K36: 15 | L36: =IF(K36="",0,K36) -> 15 | M36: 1850 | N36: =IF(M36="",0,M36) -> 1850 | O36: =IF(L36<0,"NEGATIVE QUANTITY","") | P36: =ABS(L36) -> 15 | Q36: =VLOOKUP(H36,'Product Cost Lookup'!A:D,4,FALSE) -> 1200 | R36: =VLOOKUP(H36,'Product Cost Lookup'!A:D,3,FALSE) -> Kitchenware | S36: =P36*N36 -> 27750 | T36: =P36*Q36 -> 18000 | U36: =S36-T36 -> 9750 | V36: =IF(S36=0,0,U36/S36) -> 0.35135135 | W36: =TEXT(C36,"mmm") -> Jan
A37: 10184 | B37: 45308 | C37: 45308 | D37: ELDORET | E37: =IF(TRIM(D37)="","Unknown",PROPER(TRIM(D37))) -> Eldoret | F37: Aisha Hassan | G37: =PROPER(TRIM(F37)) -> Aisha Hassan | H37: P013 | I37: Kitchen Knife Set | J37: =PROPER(TRIM(I37)) -> Kitchen Knife Set | K37: 6 | L37: =IF(K37="",0,K37) -> 6 | M37: 1250 | N37: =IF(M37="",0,M37) -> 1250 | O37: =IF(L37<0,"NEGATIVE QUANTITY","") | P37: =ABS(L37) -> 6 | Q37: =VLOOKUP(H37,'Product Cost Lookup'!A:D,4,FALSE) -> 800 | R37: =VLOOKUP(H37,'Product Cost Lookup'!A:D,3,FALSE) -> Kitchenware | S37: =P37*N37 -> 7500 | T37: =P37*Q37 -> 4800 | U37: =S37-T37 -> 2700 | V37: =IF(S37=0,0,U37/S37) -> 0.36 | W37: =TEXT(C37,"mmm") -> Jan
A38: 10062 | B38: 45375 | C38: 45375 | D38: Mombasa | E38: =IF(TRIM(D38)="","Unknown",PROPER(TRIM(D38))) -> Mombasa | F38: Aisha Hassan | G38: =PROPER(TRIM(F38)) -> Aisha Hassan | H38: P001 | I38: 20L Jerrycan - Blue | J38: =PROPER(TRIM(I38)) -> 20L Jerrycan - Blue | K38: 3 | L38: =IF(K38="",0,K38) -> 3 | M38: 650 | N38: =IF(M38="",0,M38) -> 650 | O38: =IF(L38<0,"NEGATIVE QUANTITY","") | P38: =ABS(L38) -> 3 | Q38: =VLOOKUP(H38,'Product Cost Lookup'!A:D,4,FALSE) -> 350 | R38: =VLOOKUP(H38,'Product Cost Lookup'!A:D,3,FALSE) -> Household | S38: =P38*N38 -> 1950 | T38: =P38*Q38 -> 1050 | U38: =S38-T38 -> 900 | V38: =IF(S38=0,0,U38/S38) -> 0.46153846 | W38: =TEXT(C38,"mmm") -> Mar
A39: 10296 | B39: 45375 | C39: 45375 | D39: ELDORET | E39: =IF(TRIM(D39)="","Unknown",PROPER(TRIM(D39))) -> Eldoret | F39: Samuel Kiptoo | G39: =PROPER(TRIM(F39)) -> Samuel Kiptoo | H39: P012 | I39: Garden Hose 20m | J39: =PROPER(TRIM(I39)) -> Garden Hose 20M | K39: 15 | L39: =IF(K39="",0,K39) -> 15 | M39: 1650 | N39: =IF(M39="",0,M39) -> 1650 | O39: =IF(L39<0,"NEGATIVE QUANTITY","") | P39: =ABS(L39) -> 15 | Q39: =VLOOKUP(H39,'Product Cost Lookup'!A:D,4,FALSE) -> 1100 | R39: =VLOOKUP(H39,'Product Cost Lookup'!A:D,3,FALSE) -> Hardware | S39: =P39*N39 -> 24750 | T39: =P39*Q39 -> 16500 | U39: =S39-T39 -> 8250 | V39: =IF(S39=0,0,U39/S39) -> 0.33333333 | W39: =TEXT(C39,"mmm") -> Mar
A40: 10186 | B40: 45303 | C40: 45303 | D40: Thika | E40: =IF(TRIM(D40)="","Unknown",PROPER(TRIM(D40))) -> Thika | F40: Grace Achieng | G40: =PROPER(TRIM(F40)) -> Grace Achieng | H40: P001 | I40: 20L Jerrycan - Blue | J40: =PROPER(TRIM(I40)) -> 20L Jerrycan - Blue | K40: 4 | L40: =IF(K40="",0,K40) -> 4 | M40: 600 | N40: =IF(M40="",0,M40) -> 600 | O40: =IF(L40<0,"NEGATIVE QUANTITY","") | P40: =ABS(L40) -> 4 | Q40: =VLOOKUP(H40,'Product Cost Lookup'!A:D,4,FALSE) -> 350 | R40: =VLOOKUP(H40,'Product Cost Lookup'!A:D,3,FALSE) -> Household | S40: =P40*N40 -> 2400 | T40: =P40*Q40 -> 1400 | U40: =S40-T40 -> 1000 | V40: =IF(S40=0,0,U40/S40) -> 0.41666667 | W40: =TEXT(C40,"mmm") -> Jan
A41: 10311 | B41: 45332 | C41: 45332 | D41: Thika | E41: =IF(TRIM(D41)="","Unknown",PROPER(TRIM(D41))) -> Thika | F41: Samuel Kiptoo | G41: =PROPER(TRIM(F41)) -> Samuel Kiptoo | H41: P012 | I41: Garden Hose 20m | J41: =PROPER(TRIM(I41)) -> Garden Hose 20M | K41: 5 | L41: =IF(K41="",0,K41) -> 5 | M41: 1800 | N41: =IF(M41="",0,M41) -> 1800 | O41: =IF(L41<0,"NEGATIVE QUANTITY","") | P41: =ABS(L41) -> 5 | Q41: =VLOOKUP(H41,'Product Cost Lookup'!A:D,4,FALSE) -> 1100 | R41: =VLOOKUP(H41,'Product Cost Lookup'!A:D,3,FALSE) -> Hardware | S41: =P41*N41 -> 9000 | T41: =P41*Q41 -> 5500 | U41: =S41-T41 -> 3500 | V41: =IF(S41=0,0,U41/S41) -> 0.38888889 | W41: =TEXT(C41,"mmm") -> Feb
A42: 10170 | B42: 45336 | C42: 45336 | D42: Nairobi | E42: =IF(TRIM(D42)="","Unknown",PROPER(TRIM(D42))) -> Nairobi | F42: AISHA HASSAN | G42: =PROPER(TRIM(F42)) -> Aisha Hassan | H42: P002 | I42: solar lantern sl-200 | J42: =PROPER(TRIM(I42)) -> Solar Lantern Sl-200 | K42: 5 | L42: =IF(K42="",0,K42) -> 5 | M42: 1500 | N42: =IF(M42="",0,M42) -> 1500 | O42: =IF(L42<0,"NEGATIVE QUANTITY","") | P42: =ABS(L42) -> 5 | Q42: =VLOOKUP(H42,'Product Cost Lookup'!A:D,4,FALSE) -> 900 | R42: =VLOOKUP(H42,'Product Cost Lookup'!A:D,3,FALSE) -> Electronics | S42: =P42*N42 -> 7500 | T42: =P42*Q42 -> 4500 | U42: =S42-T42 -> 3000 | V42: =IF(S42=0,0,U42/S42) -> 0.4 | W42: =TEXT(C42,"mmm") -> Feb
... A46: 10284 | B46: 45358 | C46: 45358 | D46: Thika | E46: =IF(TRIM(D46)="","Unknown",PROPER(TRIM(D46))) -> Thika | F46: samuel kiptoo | G46: =PROPER(TRIM(F46)) -> Samuel Kiptoo | H46: P014 | I46: LED Bulb 9W (Pack of 4) | J46: =PROPER(TRIM(I46)) -> Led Bulb 9W (Pack Of 4) | K46: 5 | L46: =IF(K46="",0,K46) -> 5 | M46: 880 | N46: =IF(M46="",0,M46) -> 880 | O46: =IF(L46<0,"NEGATIVE QUANTITY","") | P46: =ABS(L46) -> 5 | Q46: =VLOOKUP(H46,'Product Cost Lookup'!A:D,4,FALSE) -> 480 | R46: =VLOOKUP(H46,'Product Cost Lookup'!A:D,3,FALSE) -> Electronics | S46: =P46*N46 -> 4400 | T46: =P46*Q46 -> 2400 | U46: =S46-T46 -> 2000 | V46: =IF(S46=0,0,U46/S46) -> 0.45454545 | W46: =TEXT(C46,"mmm") -> Mar
A47: 10125 | B47: 18/01/2024 | C47: 45309 | D47: Thika | E47: =IF(TRIM(D47)="","Unknown",PROPER(TRIM(D47))) -> Thika | F47: Mercy Njeri | G47: =PROPER(TRIM(F47)) -> Mercy Njeri | H47: P013 | I47: Kitchen Knife Set | J47: =PROPER(TRIM(I47)) -> Kitchen Knife Set | K47: 10 | L47: =IF(K47="",0,K47) -> 10 | M47: 1400 | N47: =IF(M47="",0,M47) -> 1400 | O47: =IF(L47<0,"NEGATIVE QUANTITY","") | P47: =ABS(L47) -> 10 | Q47: =VLOOKUP(H47,'Product Cost Lookup'!A:D,4,FALSE) -> 800 | R47: =VLOOKUP(H47,'Product Cost Lookup'!A:D,3,FALSE) -> Kitchenware | S47: =P47*N47 -> 14000 | T47: =P47*Q47 -> 8000 | U47: =S47-T47 -> 6000 | V47: =IF(S47=0,0,U47/S47) -> 0.42857143 | W47: =TEXT(C47,"mmm") -> Jan
A48: 10173 | B48: 45367 | C48: 45367 | D48: Nakuru | E48: =IF(TRIM(D48)="","Unknown",PROPER(TRIM(D48))) -> Nakuru | F48: Brian Mutua | G48: =PROPER(TRIM(F48)) -> Brian Mutua | H48: P001 | I48: 20L Jerrycan - Blue | J48: =PROPER(TRIM(I48)) -> 20L Jerrycan - Blue | K48: 4 | L48: =IF(K48="",0,K48) -> 4 | M48: 550 | N48: =IF(M48="",0,M48) -> 550 | O48: =IF(L48<0,"NEGATIVE QUANTITY","") | P48: =ABS(L48) -> 4 | Q48: =VLOOKUP(H48,'Product Cost Lookup'!A:D,4,FALSE) -> 350 | R48: =VLOOKUP(H48,'Product Cost Lookup'!A:D,3,FALSE) -> Household | S48: =P48*N48 -> 2200 | T48: =P48*Q48 -> 1400 | U48: =S48-T48 -> 800 | V48: =IF(S48=0,0,U48/S48) -> 0.36363636 | W48: =TEXT(C48,"mmm") -> Mar
A49: 10312 | B49: 45294 | C49: 45294 | D49: Mombasa | E49: =IF(TRIM(D49)="","Unknown",PROPER(TRIM(D49))) -> Mombasa | F49: Faith Wanjiru | G49: =PROPER(TRIM(F49)) -> Faith Wanjiru | H49: P011 | I49: Padlock Set (3pc) | J49: =PROPER(TRIM(I49)) -> Padlock Set (3Pc) | K49: 5 | L49: =IF(K49="",0,K49) -> 5 | M49: 650 | N49: =IF(M49="",0,M49) -> 650 | O49: =IF(L49<0,"NEGATIVE QUANTITY","") | P49: =ABS(L49) -> 5 | Q49: =VLOOKUP(H49,'Product Cost Lookup'!A:D,4,FALSE) -> 450 | R49: =VLOOKUP(H49,'Product Cost Lookup'!A:D,3,FALSE) -> Hardware | S49: =P49*N49 -> 3250 | T49: =P49*Q49 -> 2250 | U49: =S49-T49 -> 1000 | V49: =IF(S49=0,0,U49/S49) -> 0.30769231 | W49: =TEXT(C49,"mmm") -> Jan
A50: 10115 | B50: 45599 | C50: 45599 | D50: Mombasa | E50: =IF(TRIM(D50)="","Unknown",PROPER(TRIM(D50))) -> Mombasa | F50: grace achieng | G50: =PROPER(TRIM(F50)) -> Grace Achieng | H50: P002 | I50: SOLAR LANTERN SL-200 | J50: =PROPER(TRIM(I50)) -> Solar Lantern Sl-200 | K50: 5 | L50: =IF(K50="",0,K50) -> 5 | M50: 1500 | N50: =IF(M50="",0,M50) -> 1500 | O50: =IF(L50<0,"NEGATIVE QUANTITY","") | P50: =ABS(L50) -> 5 | Q50: =VLOOKUP(H50,'Product Cost Lookup'!A:D,4,FALSE) -> 900 | R50: =VLOOKUP(H50,'Product Cost Lookup'!A:D,3,FALSE) -> Electronics | S50: =P50*N50 -> 7500 | T50: =P50*Q50 -> 4500 | U50: =S50-T50 -> 3000 | V50: =IF(S50=0,0,U50/S50) -> 0.4 | W50: =TEXT(C50,"mmm") -> Nov
A51: 10291 | B51: 45353 | C51: 45353 | D51: Nakuru | E51: =IF(TRIM(D51)="","Unknown",PROPER(TRIM(D51))) -> Nakuru | F51: Mercy Njeri | G51: =PROPER(TRIM(F51)) -> Mercy Njeri | H51: P010 | I51: Wheelbarrow Heavy Duty | J51: =PROPER(TRIM(I51)) -> Wheelbarrow Heavy Duty | K51: 15 | L51: =IF(K51="",0,K51) -> 15 | M51: 5150 | N51: =IF(M51="",0,M51) -> 5150 | O51: =IF(L51<0,"NEGATIVE QUANTITY","") | P51: =ABS(L51) -> 15 | Q51: =VLOOKUP(H51,'Product Cost Lookup'!A:D,4,FALSE) -> 3500 | R51: =VLOOKUP(H51,'Product Cost Lookup'!A:D,3,FALSE) -> Hardware | S51: =P51*N51 -> 77250 | T51: =P51*Q51 -> 52500 | U51: =S51-T51 -> 24750 | V51: =IF(S51=0,0,U51/S51) -> 0.32038835 | W51: =TEXT(C51,"mmm") -> Mar
A52: 10234 | B52: 45376 | C52: 45376 | D52: kisumu | E52: =IF(TRIM(D52)="","Unknown",PROPER(TRIM(D52))) -> Kisumu | F52: Samuel Kiptoo | G52: =PROPER(TRIM(F52)) -> Samuel Kiptoo | H52: P005 | I52: Non-Stick Frying Pan 28cm | J52: =PROPER(TRIM(I52)) -> Non-Stick Frying Pan 28Cm | K52: 20 | L52: =IF(K52="",0,K52) -> 20 | M52: 1050 | N52: =IF(M52="",0,M52) -> 1050 | O52: =IF(L52<0,"NEGATIVE QUANTITY","") | P52: =ABS(L52) -> 20 | Q52: =VLOOKUP(H52,'Product Cost Lookup'!A:D,4,FALSE) -> 700 | R52: =VLOOKUP(H52,'Product Cost Lookup'!A:D,3,FALSE) -> Kitchenware | S52: =P52*N52 -> 21000 | T52: =P52*Q52 -> 14000 | U52: =S52-T52 -> 7000 | V52: =IF(S52=0,0,U52/S52) -> 0.33333333 | W52: =TEXT(C52,"mmm") -> Mar
A53: 10335 | B53: 45374 | C53: 45374 | D53: Kisumu | E53: =IF(TRIM(D53)="","Unknown",PROPER(TRIM(D53))) -> Kisumu | F53: John Mwangi | G53: =PROPER(TRIM(F53)) -> John Mwangi | H53: P012 | I53: Garden Hose 20m | J53: =PROPER(TRIM(I53)) -> Garden Hose 20M | K53: 15 | L53: =IF(K53="",0,K53) -> 15 | M53: 1750 | N53: =IF(M53="",0,M53) -> 1750 | O53: =IF(L53<0,"NEGATIVE QUANTITY","") | P53: =ABS(L53) -> 15 | Q53: =VLOOKUP(H53,'Product Cost Lookup'!A:D,4,FALSE) -> 1100 | R53: =VLOOKUP(H53,'Product Cost Lookup'!A:D,3,FALSE) -> Hardware | S53: =P53*N53 -> 26250 | T53: =P53*Q53 -> 16500 | U53: =S53-T53 -> 9750 | V53: =IF(S53=0,0,U53/S53) -> 0.37142857 | W53: =TEXT(C53,"mmm") -> Mar
A54: 10041 | B54: 45312 | C54: 45312 | D54: Kisumu | E54: =IF(TRIM(D54)="","Unknown",PROPER(TRIM(D54))) -> Kisumu | F54: Grace Achieng | G54: =PROPER(TRIM(F54)) -> Grace Achieng | H54: P010 | I54: Wheelbarrow - Heavy Duty | J54: =PROPER(TRIM(I54)) -> Wheelbarrow - Heavy Duty | K54: 1 | L54: =IF(K54="",0,K54) -> 1 | M54: 5200 | N54: =IF(M54="",0,M54) -> 5200 | O54: =IF(L54<0,"NEGATIVE QUANTITY","") | P54: =ABS(L54) -> 1 | Q54: =VLOOKUP(H54,'Product Cost Lookup'!A:D,4,FALSE) -> 3500 | R54: =VLOOKUP(H54,'Product Cost Lookup'!A:D,3,FALSE) -> Hardware | S54: =P54*N54 -> 5200 | T54: =P54*Q54 -> 3500 | U54: =S54-T54 -> 1700 | V54: =IF(S54=0,0,U54/S54) -> 0.32692308 | W54: =TEXT(C54,"mmm") -> Jan
A55: 10093 | B55: 45445 | C55: 45445 | D55: Nairobi | E55: =IF(TRIM(D55)="","Unknown",PROPER(TRIM(D55))) -> Nairobi | F55: Grace Achieng | G55: =PROPER(TRIM(F55)) -> Grace Achieng | H55: P010 | I55: Wheelbarrow - Heavy Duty | J55: =PROPER(TRIM(I55)) -> Wheelbarrow - Heavy Duty | K55: 15 | L55: =IF(K55="",0,K55) -> 15 | M55: 5300 | N55: =IF(M55="",0,M55) -> 5300 | O55: =IF(L55<0,"NEGATIVE QUANTITY","") | P55: =ABS(L55) -> 15 | Q55: =VLOOKUP(H55,'Product Cost Lookup'!A:D,4,FALSE) -> 3500 | R55: =VLOOKUP(H55,'Product Cost Lookup'!A:D,3,FALSE) -> Hardware | S55: =P55*N55 -> 79500 | T55: =P55*Q55 -> 52500 | U55: =S55-T55 -> 27000 | V55: =IF(S55=0,0,U55/S55) -> 0.33962264 | W55: =TEXT(C55,"mmm") -> Jun
A56: 10018 | B56: 45446 | C56: 45446 | D56: Nairobi | E56: =IF(TRIM(D56)="","Unknown",PROPER(TRIM(D56))) -> Nairobi | F56: Peter Otieno | G56: =PROPER(TRIM(F56)) -> Peter Otieno | H56: P002 | I56: SOLAR LANTERN SL-200 | J56: =PROPER(TRIM(I56)) -> Solar Lantern Sl-200 | K56: 15 | L56: =IF(K56="",0,K56) -> 15 | M56: 1400 | N56: =IF(M56="",0,M56) -> 1400 | O56: =IF(L56<0,"NEGATIVE QUANTITY","") | P56: =ABS(L56) -> 15 | Q56: =VLOOKUP(H56,'Product Cost Lookup'!A:D,4,FALSE) -> 900 | R56: =VLOOKUP(H56,'Product Cost Lookup'!A:D,3,FALSE) -> Electronics | S56: =P56*N56 -> 21000 | T56: =P56*Q56 -> 13500 | U56: =S56-T56 -> 7500 | V56: =IF(S56=0,0,U56/S56) -> 0.35714286 | W56: =TEXT(C56,"mmm") -> Jun
A57: 10209 | B57: 45337 | C57: 45337 | E57: =IF(TRIM(D57)="","Unknown",PROPER(TRIM(D57))) -> Unknown | F57: Aisha Hassan | G57: =PROPER(TRIM(F57)) -> Aisha Hassan | H57: P006 | I57: Plastic Storage Basket (L) | J57: =PROPER(TRIM(I57)) -> Plastic Storage Basket (L) | K57: 15 | L57: =IF(K57="",0,K57) -> 15 | M57: 520 | N57: =IF(M57="",0,M57) -> 520 | O57: =IF(L57<0,"NEGATIVE QUANTITY","") | P57: =ABS(L57) -> 15 | Q57: =VLOOKUP(H57,'Product Cost Lookup'!A:D,4,FALSE) -> 250 | R57: =VLOOKUP(H57,'Product Cost Lookup'!A:D,3,FALSE) -> Household | S57: =P57*N57 -> 7800 | T57: =P57*Q57 -> 3750 | U57: =S57-T57 -> 4050 | V57: =IF(S57=0,0,U57/S57) -> 0.51923077 | W57: =TEXT(C57,"mmm") -> Feb
A58: 10298 | B58: 45358 | C58: 45358 | D58: nairobi | E58: =IF(TRIM(D58)="","Unknown",PROPER(TRIM(D58))) -> Nairobi | F58: Grace Achieng | G58: =PROPER(TRIM(F58)) -> Grace Achieng | H58: P015 | I58: Water Dispenser Stand | J58: =PROPER(TRIM(I58)) -> Water Dispenser Stand | K58: 2 | L58: =IF(K58="",0,K58) -> 2 | M58: 2400 | N58: =IF(M58="",0,M58) -> 2400 | O58: =IF(L58<0,"NEGATIVE QUANTITY","") | P58: =ABS(L58) -> 2 | Q58: =VLOOKUP(H58,'Product Cost Lookup'!A:D,4,FALSE) -> 1500 | R58: =VLOOKUP(H58,'Product Cost Lookup'!A:D,3,FALSE) -> Household | S58: =P58*N58 -> 4800 | T58: =P58*Q58 -> 3000 | U58: =S58-T58 -> 1800 | V58: =IF(S58=0,0,U58/S58) -> 0.375 | W58: =TEXT(C58,"mmm") -> Mar
A59: 10080 | B59: 45356 | C59: 45356 | D59: eldoret | E59: =IF(TRIM(D59)="","Unknown",PROPER(TRIM(D59))) -> Eldoret | F59: Brian Mutua | G59: =PROPER(TRIM(F59)) -> Brian Mutua | H59: P002 | I59: solar lantern sl-200 | J59: =PROPER(TRIM(I59)) -> Solar Lantern Sl-200 | K59: 2 | L59: =IF(K59="",0,K59) -> 2 | M59: 1550 | N59: =IF(M59="",0,M59) -> 1550 | O59: =IF(L59<0,"NEGATIVE QUANTITY","") | P59: =ABS(L59) -> 2 | Q59: =VLOOKUP(H59,'Product Cost Lookup'!A:D,4,FALSE) -> 900 | R59: =VLOOKUP(H59,'Product Cost Lookup'!A:D,3,FALSE) -> Electronics | S59: =P59*N59 -> 3100 | T59: =P59*Q59 -> 1800 | U59: =S59-T59 -> 1300 | V59: =IF(S59=0,0,U59/S59) -> 0.41935484 | W59: =TEXT(C59,"mmm") -> Mar
A60: 10099 | B60: 45378 | C60: 45378 | D60: Thika | E60: =IF(TRIM(D60)="","Unknown",PROPER(TRIM(D60))) -> Thika | F60: Faith Wanjiru | G60: =PROPER(TRIM(F60)) -> Faith Wanjiru | H60: P008 | I60: USB Wall Charger UC-5 | J60: =PROPER(TRIM(I60)) -> Usb Wall Charger Uc-5 | K60: 15 | L60: =IF(K60="",0,K60) -> 15 | M60: 500 | N60: =IF(M60="",0,M60) -> 500 | O60: =IF(L60<0,"NEGATIVE QUANTITY","") | P60: =ABS(L60) -> 15 | Q60: =VLOOKUP(H60,'Product Cost Lookup'!A:D,4,FALSE) -> 300 | R60: =VLOOKUP(H60,'Product Cost Lookup'!A:D,3,FALSE) -> Electronics | S60: =P60*N60 -> 7500 | T60: =P60*Q60 -> 4500 | U60: =S60-T60 -> 3000 | V60: =IF(S60=0,0,U60/S60) -> 0.4 | W60: =TEXT(C60,"mmm") -> Mar
A61: 10012 | B61: 45319 | C61: 45319 | D61: Eldoret | E61: =IF(TRIM(D61)="","Unknown",PROPER(TRIM(D61))) -> Eldoret | F61: faith wanjiru | G61: =PROPER(TRIM(F61)) -> Faith Wanjiru | H61: P012 | I61: Garden Hose 20m | J61: =PROPER(TRIM(I61)) -> Garden Hose 20M | K61: 5 | L61: =IF(K61="",0,K61) -> 5 | M61: 1750 | N61: =IF(M61="",0,M61) -> 1750 | O61: =IF(L61<0,"NEGATIVE QUANTITY","") | P61: =ABS(L61) -> 5 | Q61: =VLOOKUP(H61,'Product Cost Lookup'!A:D,4,FALSE) -> 1100 | R61: =VLOOKUP(H61,'Product Cost Lookup'!A:D,3,FALSE) -> Hardware | S61: =P61*N61 -> 8750 | T61: =P61*Q61 -> 5500 | U61: =S61-T61 -> 3250 | V61: =IF(S61=0,0,U61/S61) -> 0.37142857 | W61: =TEXT(C61,"mmm") -> Jan
A62: 10246 | B62: 45312 | C62: 45312 | D62: Nairobi | E62: =IF(TRIM(D62)="","Unknown",PROPER(TRIM(D62))) -> Nairobi | F62: Aisha Hassan | G62: =PROPER(TRIM(F62)) -> Aisha Hassan | H62: P015 | I62: WATER DISPENSER STAND | J62: =PROPER(TRIM(I62)) -> Water Dispenser Stand | K62: 4 | L62: =IF(K62="",0,K62) -> 4 | N62: =IF(M62="",0,M62) -> 0 | O62: =IF(L62<0,"NEGATIVE QUANTITY","") | P62: =ABS(L62) -> 4 | Q62: =VLOOKUP(H62,'Product Cost Lookup'!A:D,4,FALSE) -> 1500 | R62: =VLOOKUP(H62,'Product Cost Lookup'!A:D,3,FALSE) -> Household | S62: =P62*N62 -> 0 | T62: =P62*Q62 -> 6000 | U62: =S62-T62 -> -6000 | V62: =IF(S62=0,0,U62/S62) -> 0 | W62: =TEXT(C62,"mmm") -> Jan
A63: 10097 | B63: 45374 | C63: 45374 | D63: kisumu | E63: =IF(TRIM(D63)="","Unknown",PROPER(TRIM(D63))) -> Kisumu | F63: Peter Otieno | G63: =PROPER(TRIM(F63)) -> Peter Otieno | H63: P011 | I63: Padlock Set (3pc) | J63: =PROPER(TRIM(I63)) -> Padlock Set (3Pc) | K63: 20 | L63: =IF(K63="",0,K63) -> 20 | M63: 800 | N63: =IF(M63="",0,M63) -> 800 | O63: =IF(L63<0,"NEGATIVE QUANTITY","") | P63: =ABS(L63) -> 20 | Q63: =VLOOKUP(H63,'Product Cost Lookup'!A:D,4,FALSE) -> 450 | R63: =VLOOKUP(H63,'Product Cost Lookup'!A:D,3,FALSE) -> Hardware | S63: =P63*N63 -> 16000 | T63: =P63*Q63 -> 9000 | U63: =S63-T63 -> 7000 | V63: =IF(S63=0,0,U63/S63) -> 0.4375 | W63: =TEXT(C63,"mmm") -> Mar
A64: 10337 | B64: 45303 | C64: 45303 | D64: Mombasa | E64: =IF(TRIM(D64)="","Unknown",PROPER(TRIM(D64))) -> Mombasa | F64: Brian Mutua | G64: =PROPER(TRIM(F64)) -> Brian Mutua | H64: P005 | I64: Non-Stick Frying Pan 28cm | J64: =PROPER(TRIM(I64)) -> Non-Stick Frying Pan 28Cm | K64: 8 | L64: =IF(K64="",0,K64) -> 8 | M64: 1100 | N64: =IF(M64="",0,M64) -> 1100 | O64: =IF(L64<0,"NEGATIVE QUANTITY","") | P64: =ABS(L64) -> 8 | Q64: =VLOOKUP(H64,'Product Cost Lookup'!A:D,4,FALSE) -> 700 | R64: =VLOOKUP(H64,'Product Cost Lookup'!A:D,3,FALSE) -> Kitchenware | S64: =P64*N64 -> 8800 | T64: =P64*Q64 -> 5600 | U64: =S64-T64 -> 3200 | V64: =IF(S64=0,0,U64/S64) -> 0.36363636 | W64: =TEXT(C64,"mmm") -> Jan
A65: 10330 | B65: 45372 | C65: 45372 | D65: Mombasa | E65: =IF(TRIM(D65)="","Unknown",PROPER(TRIM(D65))) -> Mombasa | F65: Brian Mutua | G65: =PROPER(TRIM(F65)) -> Brian Mutua | H65: P012 | I65: Garden Hose 20m | J65: =PROPER(TRIM(I65)) -> Garden Hose 20M | K65: 2 | L65: =IF(K65="",0,K65) -> 2 | M65: 1800 | N65: =IF(M65="",0,M65) -> 1800 | O65: =IF(L65<0,"NEGATIVE QUANTITY","") | P65: =ABS(L65) -> 2 | Q65: =VLOOKUP(H65,'Product Cost Lookup'!A:D,4,FALSE) -> 1100 | R65: =VLOOKUP(H65,'Product Cost Lookup'!A:D,3,FALSE) -> Hardware | S65: =P65*N65 -> 3600 | T65: =P65*Q65 -> 2200 | U65: =S65-T65 -> 1400 | V65: =IF(S65=0,0,U65/S65) -> 0.38888889 | W65: =TEXT(C65,"mmm") -> Mar
A66: 10151 | B66: 45332 | C66: 45332 | D66: Mombasa | E66: =IF(TRIM(D66)="","Unknown",PROPER(TRIM(D66))) -> Mombasa | F66: Mercy Njeri | G66: =PROPER(TRIM(F66)) -> Mercy Njeri | H66: P006 | I66: Plastic Storage Basket (L) | J66: =PROPER(TRIM(I66)) -> Plastic Storage Basket (L) | K66: 8 | L66: =IF(K66="",0,K66) -> 8 | M66: 370 | N66: =IF(M66="",0,M66) -> 370 | O66: =IF(L66<0,"NEGATIVE QUANTITY","") | P66: =ABS(L66) -> 8 | Q66: =VLOOKUP(H66,'Product Cost Lookup'!A:D,4,FALSE) -> 250 | R66: =VLOOKUP(H66,'Product Cost Lookup'!A:D,3,FALSE) -> Household | S66: =P66*N66 -> 2960 | T66: =P66*Q66 -> 2000 | U66: =S66-T66 -> 960 | V66: =IF(S66=0,0,U66/S66) -> 0.32432432 | W66: =TEXT(C66,"mmm") -> Feb
A67: 10264 | B67: 45322 | C67: 45322 | D67: Eldoret | E67: =IF(TRIM(D67)="","Unknown",PROPER(TRIM(D67))) -> Eldoret | F67: Samuel Kiptoo | G67: =PROPER(TRIM(F67)) -> Samuel Kiptoo | H67: P012 | I67: Garden Hose 20m | J67: =PROPER(TRIM(I67)) -> Garden Hose 20M | K67: 20 | L67: =IF(K67="",0,K67) -> 20 | M67: 1650 | N67: =IF(M67="",0,M67) -> 1650 | O67: =IF(L67<0,"NEGATIVE QUANTITY","") | P67: =ABS(L67) -> 20 | Q67: =VLOOKUP(H67,'Product Cost Lookup'!A:D,4,FALSE) -> 1100 | R67: =VLOOKUP(H67,'Product Cost Lookup'!A:D,3,FALSE) -> Hardware | S67: =P67*N67 -> 33000 | T67: =P67*Q67 -> 22000 | U67: =S67-T67 -> 11000 | V67: =IF(S67=0,0,U67/S67) -> 0.33333333 | W67: =TEXT(C67,"mmm") -> Jan
A68: 10280 | B68: 45353 | C68: 45353 | D68: Thika | E68: =IF(TRIM(D68)="","Unknown",PROPER(TRIM(D68))) -> Thika | F68: Grace Achieng | G68: =PROPER(TRIM(F68)) -> Grace Achieng | H68: P012 | I68: Garden Hose 20m | J68: =PROPER(TRIM(I68)) -> Garden Hose 20M | K68: 2 | L68: =IF(K68="",0,K68) -> 2 | M68: 1650 | N68: =IF(M68="",0,M68) -> 1650 | O68: =IF(L68<0,"NEGATIVE QUANTITY","") | P68: =ABS(L68) -> 2 | Q68: =VLOOKUP(H68,'Product Cost Lookup'!A:D,4,FALSE) -> 1100 | R68: =VLOOKUP(H68,'Product Cost Lookup'!A:D,3,FALSE) -> Hardware | S68: =P68*N68 -> 3300 | T68: =P68*Q68 -> 2200 | U68: =S68-T68 -> 1100 | V68: =IF(S68=0,0,U68/S68) -> 0.33333333 | W68: =TEXT(C68,"mmm") -> Mar
A69: 10072 | B69: 14/01/2024 | C69: 45305 | D69: Thika | E69: =IF(TRIM(D69)="","Unknown",PROPER(TRIM(D69))) -> Thika | F69: Faith Wanjiru | G69: =PROPER(TRIM(F69)) -> Faith Wanjiru | H69: P008 | I69: USB Wall Charger UC-5 | J69: =PROPER(TRIM(I69)) -> Usb Wall Charger Uc-5 | K69: 1 | L69: =IF(K69="",0,K69) -> 1 | M69: 600 | N69: =IF(M69="",0,M69) -> 600 | O69: =IF(L69<0,"NEGATIVE QUANTITY","") | P69: =ABS(L69) -> 1 | Q69: =VLOOKUP(H69,'Product Cost Lookup'!A:D,4,FALSE) -> 300 | R69: =VLOOKUP(H69,'Product Cost Lookup'!A:D,3,FALSE) -> Electronics | S69: =P69*N69 -> 600 | T69: =P69*Q69 -> 300 | U69: =S69-T69 -> 300 | V69: =IF(S69=0,0,U69/S69) -> 0.5 | W69: =TEXT(C69,"mmm") -> Jan
A70: 10077 | B70: 45376 | C70: 45376 | D70: Nairobi | E70: =IF(TRIM(D70)="","Unknown",PROPER(TRIM(D70))) -> Nairobi | F70: Peter Otieno | G70: =PROPER(TRIM(F70)) -> Peter Otieno | H70: P001 | I70: 20L Jerrycan - Blue | J70: =PROPER(TRIM(I70)) -> 20L Jerrycan - Blue | K70: 6 | L70: =IF(K70="",0,K70) -> 6 | N70: =IF(M70="",0,M70) -> 0 | O70: =IF(L70<0,"NEGATIVE QUANTITY","") | P70: =ABS(L70) -> 6 | Q70: =VLOOKUP(H70,'Product Cost Lookup'!A:D,4,FALSE) -> 350 | R70: =VLOOKUP(H70,'Product Cost Lookup'!A:D,3,FALSE) -> Household | S70: =P70*N70 -> 0 | T70: =P70*Q70 -> 2100 | U70: =S70-T70 -> -2100 | V70: =IF(S70=0,0,U70/S70) -> 0 | W70: =TEXT(C70,"mmm") -> Mar
A71: 10201 | B71: 19/01/2024 | C71: 45310 | D71: Thika | E71: =IF(TRIM(D71)="","Unknown",PROPER(TRIM(D71))) -> Thika | F71: SAMUEL KIPTOO | G71: =PROPER(TRIM(F71)) -> Samuel Kiptoo | H71: P002 | I71: SOLAR LANTERN SL-200 | J71: =PROPER(TRIM(I71)) -> Solar Lantern Sl-200 | K71: 1 | L71: =IF(K71="",0,K71) -> 1 | M71: 1450 | N71: =IF(M71="",0,M71) -> 1450 | O71: =IF(L71<0,"NEGATIVE QUANTITY","") | P71: =ABS(L71) -> 1 | Q71: =VLOOKUP(H71,'Product Cost Lookup'!A:D,4,FALSE) -> 900 | R71: =VLOOKUP(H71,'Product Cost Lookup'!A:D,3,FALSE) -> Electronics | S71: =P71*N71 -> 1450 | T71: =P71*Q71 -> 900 | U71: =S71-T71 -> 550 | V71: =IF(S71=0,0,U71/S71) -> 0.37931034 | W71: =TEXT(C71,"mmm") -> Jan
A72: 10204 | B72: 45379 | C72: 45379 | D72: Kisumu | E72: =IF(TRIM(D72)="","Unknown",PROPER(TRIM(D72))) -> Kisumu | F72: JOHN MWANGI | G72: =PROPER(TRIM(F72)) -> John Mwangi | H72: P004 | I72: Cooking Gas Burner CB-2 | J72: =PROPER(TRIM(I72)) -> Cooking Gas Burner Cb-2 | K72: 6 | L72: =IF(K72="",0,K72) -> 6 | M72: 1850 | N72: =IF(M72="",0,M72) -> 1850 | O72: =IF(L72<0,"NEGATIVE QUANTITY","") | P72: =ABS(L72) -> 6 | Q72: =VLOOKUP(H72,'Product Cost Lookup'!A:D,4,FALSE) -> 1200 | R72: =VLOOKUP(H72,'Product Cost Lookup'!A:D,3,FALSE) -> Kitchenware | S72: =P72*N72 -> 11100 | T72: =P72*Q72 -> 7200 | U72: =S72-T72 -> 3900 | V72: =IF(S72=0,0,U72/S72) -> 0.35135135 | W72: =TEXT(C72,"mmm") -> Mar
A73: 10176 | B73: 45373 | C73: 45373 | D73: Eldoret | E73: =IF(TRIM(D73)="","Unknown",PROPER(TRIM(D73))) -> Eldoret | F73: Peter Otieno | G73: =PROPER(TRIM(F73)) -> Peter Otieno | H73: P009 | I73: Thermos Flask 1L | J73: =PROPER(TRIM(I73)) -> Thermos Flask 1L | K73: 3 | L73: =IF(K73="",0,K73) -> 3 | M73: 950 | N73: =IF(M73="",0,M73) -> 950 | O73: =IF(L73<0,"NEGATIVE QUANTITY","") | P73: =ABS(L73) -> 3 | Q73: =VLOOKUP(H73,'Product Cost Lookup'!A:D,4,FALSE) -> 550 | R73: =VLOOKUP(H73,'Product Cost Lookup'!A:D,3,FALSE) -> Kitchenware | S73: =P73*N73 -> 2850 | T73: =P73*Q73 -> 1650 | U73: =S73-T73 -> 1200 | V73: =IF(S73=0,0,U73/S73) -> 0.42105263 | W73: =TEXT(C73,"mmm") -> Mar
A74: 10059 | B74: 45329 | C74: 45329 | D74: Eldoret | E74: =IF(TRIM(D74)="","Unknown",PROPER(TRIM(D74))) -> Eldoret | F74: Samuel Kiptoo | G74: =PROPER(TRIM(F74)) -> Samuel Kiptoo | H74: P007 | I74: Mosquito Net - Family Size | J74: =PROPER(TRIM(I74)) -> Mosquito Net - Family Size | K74: 10 | L74: =IF(K74="",0,K74) -> 10 | M74: 700 | N74: =IF(M74="",0,M74) -> 700 | O74: =IF(L74<0,"NEGATIVE QUANTITY","") | P74: =ABS(L74) -> 10 | Q74: =VLOOKUP(H74,'Product Cost Lookup'!A:D,4,FALSE) -> 400 | R74: =VLOOKUP(H74,'Product Cost Lookup'!A:D,3,FALSE) -> Household | S74: =P74*N74 -> 7000 | T74: =P74*Q74 -> 4000 | U74: =S74-T74 -> 3000 | V74: =IF(S74=0,0,U74/S74) -> 0.42857143 | W74: =TEXT(C74,"mmm") -> Feb
A75: 10002 | B75: 45295 | C75: 45295 | D75: Eldoret | E75: =IF(TRIM(D75)="","Unknown",PROPER(TRIM(D75))) -> Eldoret | F75: Faith Wanjiru | G75: =PROPER(TRIM(F75)) -> Faith Wanjiru | H75: P012 | I75: Garden Hose 20m | J75: =PROPER(TRIM(I75)) -> Garden Hose 20M | K75: 20 | L75: =IF(K75="",0,K75) -> 20 | M75: 1800 | N75: =IF(M75="",0,M75) -> 1800 | O75: =IF(L75<0,"NEGATIVE QUANTITY","") | P75: =ABS(L75) -> 20 | Q75: =VLOOKUP(H75,'Product Cost Lookup'!A:D,4,FALSE) -> 1100 | R75: =VLOOKUP(H75,'Product Cost Lookup'!A:D,3,FALSE) -> Hardware | S75: =P75*N75 -> 36000 | T75: =P75*Q75 -> 22000 | U75: =S75-T75 -> 14000 | V75: =IF(S75=0,0,U75/S75) -> 0.38888889 | W75: =TEXT(C75,"mmm") -> Jan
A76: 10189 | B76: 14/02/2024 | C76: 45336 | D76: Nakuru | E76: =IF(TRIM(D76)="","Unknown",PROPER(TRIM(D76))) -> Nakuru | F76: Mercy Njeri | G76: =PROPER(TRIM(F76)) -> Mercy Njeri | H76: P013 | I76: Kitchen Knife Set | J76: =PROPER(TRIM(I76)) -> Kitchen Knife Set | K76: 3 | L76: =IF(K76="",0,K76) -> 3 | M76: 1300 | N76: =IF(M76="",0,M76) -> 1300 | O76: =IF(L76<0,"NEGATIVE QUANTITY","") | P76: =ABS(L76) -> 3 | Q76: =VLOOKUP(H76,'Product Cost Lookup'!A:D,4,FALSE) -> 800 | R76: =VLOOKUP(H76,'Product Cost Lookup'!A:D,3,FALSE) -> Kitchenware | S76: =P76*N76 -> 3900 | T76: =P76*Q76 -> 2400 | U76: =S76-T76 -> 1500 | V76: =IF(S76=0,0,U76/S76) -> 0.38461538 | W76: =TEXT(C76,"mmm") -> Feb
A77: 10001 | B77: 45373 | C77: 45373 | D77: Nairobi | E77: =IF(TRIM(D77)="","Unknown",PROPER(TRIM(D77))) -> Nairobi | F77: John Mwangi | G77: =PROPER(TRIM(F77)) -> John Mwangi | H77: P012 | I77: Garden Hose 20m | J77: =PROPER(TRIM(I77)) -> Garden Hose 20M | K77: 5 | L77: =IF(K77="",0,K77) -> 5 | M77: 1700 | N77: =IF(M77="",0,M77) -> 1700 | O77: =IF(L77<0,"NEGATIVE QUANTITY","") | P77: =ABS(L77) -> 5 | Q77: =VLOOKUP(H77,'Product Cost Lookup'!A:D,4,FALSE) -> 1100 | R77: =VLOOKUP(H77,'Product Cost Lookup'!A:D,3,FALSE) -> Hardware | S77: =P77*N77 -> 8500 | T77: =P77*Q77 -> 5500 | U77: =S77-T77 -> 3000 | V77: =IF(S77=0,0,U77/S77) -> 0.35294118 | W77: =TEXT(C77,"mmm") -> Mar
A78: 10026 | B78: 45327 | C78: 45327 | D78: Nairobi | E78: =IF(TRIM(D78)="","Unknown",PROPER(TRIM(D78))) -> Nairobi | F78: Samuel Kiptoo | G78: =PROPER(TRIM(F78)) -> Samuel Kiptoo | H78: P006 | I78: Plastic Storage Basket (L) | J78: =PROPER(TRIM(I78)) -> Plastic Storage Basket (L) | K78: 20 | L78: =IF(K78="",0,K78) -> 20 | M78: 520 | N78: =IF(M78="",0,M78) -> 520 | O78: =IF(L78<0,"NEGATIVE QUANTITY","") | P78: =ABS(L78) -> 20 | Q78: =VLOOKUP(H78,'Product Cost Lookup'!A:D,4,FALSE) -> 250 | R78: =VLOOKUP(H78,'Product Cost Lookup'!A:D,3,FALSE) -> Household | S78: =P78*N78 -> 10400 | T78: =P78*Q78 -> 5000 | U78: =S78-T78 -> 5400 | V78: =IF(S78=0,0,U78/S78) -> 0.51923077 | W78: =TEXT(C78,"mmm") -> Feb
A79: 10281 | B79: 45352 | C79: 45352 | D79: Thika | E79: =IF(TRIM(D79)="","Unknown",PROPER(TRIM(D79))) -> Thika | F79: Peter Otieno | G79: =PROPER(TRIM(F79)) -> Peter Otieno | H79: P006 | I79: Plastic Storage Basket L | J79: =PROPER(TRIM(I79)) -> Plastic Storage Basket L | K79: 8 | L79: =IF(K79="",0,K79) -> 8 | M79: 420 | N79: =IF(M79="",0,M79) -> 420 | O79: =IF(L79<0,"NEGATIVE QUANTITY","") | P79: =ABS(L79) -> 8 | Q79: =VLOOKUP(H79,'Product Cost Lookup'!A:D,4,FALSE) -> 250 | R79: =VLOOKUP(H79,'Product Cost Lookup'!A:D,3,FALSE) -> Household | S79: =P79*N79 -> 3360 | T79: =P79*Q79 -> 2000 | U79: =S79-T79 -> 1360 | V79: =IF(S79=0,0,U79/S79) -> 0.4047619 | W79: =TEXT(C79,"mmm") -> Mar
A80: 10145 | B80: 45444 | C80: 45444 | D80: Nakuru | E80: =IF(TRIM(D80)="","Unknown",PROPER(TRIM(D80))) -> Nakuru | F80: Aisha Hassan | G80: =PROPER(TRIM(F80)) -> Aisha Hassan | H80: P004 | I80: Cooking Gas Burner CB-2 | J80: =PROPER(TRIM(I80)) -> Cooking Gas Burner Cb-2 | K80: 12 | L80: =IF(K80="",0,K80) -> 12 | M80: 1850 | N80: =IF(M80="",0,M80) -> 1850 | O80: =IF(L80<0,"NEGATIVE QUANTITY","") | P80: =ABS(L80) -> 12 | Q80: =VLOOKUP(H80,'Product Cost Lookup'!A:D,4,FALSE) -> 1200 | R80: =VLOOKUP(H80,'Product Cost Lookup'!A:D,3,FALSE) -> Kitchenware | S80: =P80*N80 -> 22200 | T80: =P80*Q80 -> 14400 | U80: =S80-T80 -> 7800 | V80: =IF(S80=0,0,U80/S80) -> 0.35135135 | W80: =TEXT(C80,"mmm") -> Jun
A81: 10141 | B81: 45294 | C81: 45294 | D81: Nakuru | E81: =IF(TRIM(D81)="","Unknown",PROPER(TRIM(D81))) -> Nakuru | F81: Samuel Kiptoo | G81: =PROPER(TRIM(F81)) -> Samuel Kiptoo | H81: P014 | I81: LED Bulb 9W (Pack of 4) | J81: =PROPER(TRIM(I81)) -> Led Bulb 9W (Pack Of 4) | K81: 1 | L81: =IF(K81="",0,K81) -> 1 | M81: 780 | N81: =IF(M81="",0,M81) -> 780 | O81: =IF(L81<0,"NEGATIVE QUANTITY","") | P81: =ABS(L81) -> 1 | Q81: =VLOOKUP(H81,'Product Cost Lookup'!A:D,4,FALSE) -> 480 | R81: =VLOOKUP(H81,'Product Cost Lookup'!A:D,3,FALSE) -> Electronics | S81: =P81*N81 -> 780 | T81: =P81*Q81 -> 480 | U81: =S81-T81 -> 300 | V81: =IF(S81=0,0,U81/S81) -> 0.38461538 | W81: =TEXT(C81,"mmm") -> Jan
A82: 10179 | B82: 45346 | C82: 45346 | D82: Nairobi | E82: =IF(TRIM(D82)="","Unknown",PROPER(TRIM(D82))) -> Nairobi | F82: Faith Wanjiru | G82: =PROPER(TRIM(F82)) -> Faith Wanjiru | H82: P005 | I82: Non-Stick Frying Pan 28cm | J82: =PROPER(TRIM(I82)) -> Non-Stick Frying Pan 28Cm | K82: 1 | L82: =IF(K82="",0,K82) -> 1 | M82: 1150 | N82: =IF(M82="",0,M82) -> 1150 | O82: =IF(L82<0,"NEGATIVE QUANTITY","") | P82: =ABS(L82) -> 1 | Q82: =VLOOKUP(H82,'Product Cost Lookup'!A:D,4,FALSE) -> 700 | R82: =VLOOKUP(H82,'Product Cost Lookup'!A:D,3,FALSE) -> Kitchenware | S82: =P82*N82 -> 1150 | T82: =P82*Q82 -> 700 | U82: =S82-T82 -> 450 | V82: =IF(S82=0,0,U82/S82) -> 0.39130435 | W82: =TEXT(C82,"mmm") -> Feb
A83: 10295 | B83: 45474 | C83: 45474 | D83: mombasa | E83: =IF(TRIM(D83)="","Unknown",PROPER(TRIM(D83))) -> Mombasa | F83: Brian Mutua | G83: =PROPER(TRIM(F83)) -> Brian Mutua | H83: P011 | I83: Padlock Set (3pc) | J83: =PROPER(TRIM(I83)) -> Padlock Set (3Pc) | K83: 1 | L83: =IF(K83="",0,K83) -> 1 | M83: 650 | N83: =IF(M83="",0,M83) -> 650 | O83: =IF(L83<0,"NEGATIVE QUANTITY","") | P83: =ABS(L83) -> 1 | Q83: =VLOOKUP(H83,'Product Cost Lookup'!A:D,4,FALSE) -> 450 | R83: =VLOOKUP(H83,'Product Cost Lookup'!A:D,3,FALSE) -> Hardware | S83: =P83*N83 -> 650 | T83: =P83*Q83 -> 450 | U83: =S83-T83 -> 200 | V83: =IF(S83=0,0,U83/S83) -> 0.30769231 | W83: =TEXT(C83,"mmm") -> Jul
A84: 10112 | B84: 45301 | C84: 45301 | D84: ELDORET | E84: =IF(TRIM(D84)="","Unknown",PROPER(TRIM(D84))) -> Eldoret | F84: Peter Otieno | G84: =PROPER(TRIM(F84)) -> Peter Otieno | H84: P009 | I84: Thermos Flask 1L | J84: =PROPER(TRIM(I84)) -> Thermos Flask 1L | K84: 6 | L84: =IF(K84="",0,K84) -> 6 | M84: 950 | N84: =IF(M84="",0,M84) -> 950 | O84: =IF(L84<0,"NEGATIVE QUANTITY","") | P84: =ABS(L84) -> 6 | Q84: =VLOOKUP(H84,'Product Cost Lookup'!A:D,4,FALSE) -> 550 | R84: =VLOOKUP(H84,'Product Cost Lookup'!A:D,3,FALSE) -> Kitchenware | S84: =P84*N84 -> 5700 | T84: =P84*Q84 -> 3300 | U84: =S84-T84 -> 2400 | V84: =IF(S84=0,0,U84/S84) -> 0.42105263 | W84: =TEXT(C84,"mmm") -> Jan
A85: 10086 | B85: 45302 | C85: 45302 | D85: Kisumu | E85: =IF(TRIM(D85)="","Unknown",PROPER(TRIM(D85))) -> Kisumu | F85: Aisha Hassan | G85: =PROPER(TRIM(F85)) -> Aisha Hassan | H85: P011 | I85: Padlock Set (3pc) | J85: =PROPER(TRIM(I85)) -> Padlock Set (3Pc) | K85: 8 | L85: =IF(K85="",0,K85) -> 8 | M85: 750 | N85: =IF(M85="",0,M85) -> 750 | O85: =IF(L85<0,"NEGATIVE QUANTITY","") | P85: =ABS(L85) -> 8 | Q85: =VLOOKUP(H85,'Product Cost Lookup'!A:D,4,FALSE) -> 450 | R85: =VLOOKUP(H85,'Product Cost Lookup'!A:D,3,FALSE) -> Hardware | S85: =P85*N85 -> 6000 | T85: =P85*Q85 -> 3600 | U85: =S85-T85 -> 2400 | V85: =IF(S85=0,0,U85/S85) -> 0.4 | W85: =TEXT(C85,"mmm") -> Jan
A86: 10040 | B86: 20/01/2024 | C86: 45311 | D86: Mombasa | E86: =IF(TRIM(D86)="","Unknown",PROPER(TRIM(D86))) -> Mombasa | F86: Peter Otieno | G86: =PROPER(TRIM(F86)) -> Peter Otieno | H86: P008 | I86: USB WALL CHARGER UC-5 | J86: =PROPER(TRIM(I86)) -> Usb Wall Charger Uc-5 | K86: 20 | L86: =IF(K86="",0,K86) -> 20 | M86: 450 | N86: =IF(M86="",0,M86) -> 450 | O86: =IF(L86<0,"NEGATIVE QUANTITY","") | P86: =ABS(L86) -> 20 | Q86: =VLOOKUP(H86,'Product Cost Lookup'!A:D,4,FALSE) -> 300 | R86: =VLOOKUP(H86,'Product Cost Lookup'!A:D,3,FALSE) -> Electronics | S86: =P86*N86 -> 9000 | T86: =P86*Q86 -> 6000 | U86: =S86-T86 -> 3000 | V86: =IF(S86=0,0,U86/S86) -> 0.33333333 | W86: =TEXT(C86,"mmm") -> Jan
A87: 10054 | B87: 45326 | C87: 45326 | D87: Eldoret | E87: =IF(TRIM(D87)="","Unknown",PROPER(TRIM(D87))) -> Eldoret | F87: Aisha Hassan | G87: =PROPER(TRIM(F87)) -> Aisha Hassan | H87: P008 | I87: USB Wall Charger UC-5 | J87: =PROPER(TRIM(I87)) -> Usb Wall Charger Uc-5 | K87: 2 | L87: =IF(K87="",0,K87) -> 2 | M87: 600 | N87: =IF(M87="",0,M87) -> 600 | O87: =IF(L87<0,"NEGATIVE QUANTITY","") | P87: =ABS(L87) -> 2 | Q87: =VLOOKUP(H87,'Product Cost Lookup'!A:D,4,FALSE) -> 300 | R87: =VLOOKUP(H87,'Product Cost Lookup'!A:D,3,FALSE) -> Electronics | S87: =P87*N87 -> 1200 | T87: =P87*Q87 -> 600 | U87: =S87-T87 -> 600 | V87: =IF(S87=0,0,U87/S87) -> 0.5 | W87: =TEXT(C87,"mmm") -> Feb
A88: 10133 | B88: 45344 | C88: 45344 | D88: Thika | E88: =IF(TRIM(D88)="","Unknown",PROPER(TRIM(D88))) -> Thika | F88: Aisha Hassan | G88: =PROPER(TRIM(F88)) -> Aisha Hassan | H88: P008 | I88: USB Wall Charger UC-5 | J88: =PROPER(TRIM(I88)) -> Usb Wall Charger Uc-5 | K88: 20 | L88: =IF(K88="",0,K88) -> 20 | M88: 500 | N88: =IF(M88="",0,M88) -> 500 | O88: =IF(L88<0,"NEGATIVE QUANTITY","") | P88: =ABS(L88) -> 20 | Q88: =VLOOKUP(H88,'Product Cost Lookup'!A:D,4,FALSE) -> 300 | R88: =VLOOKUP(H88,'Product Cost Lookup'!A:D,3,FALSE) -> Electronics | S88: =P88*N88 -> 10000 | T88: =P88*Q88 -> 6000 | U88: =S88-T88 -> 4000 | V88: =IF(S88=0,0,U88/S88) -> 0.4 | W88: =TEXT(C88,"mmm") -> Feb
A89: 10105 | B89: 16/02/2024 | C89: 45338 | D89: Nairobi | E89: =IF(TRIM(D89)="","Unknown",PROPER(TRIM(D89))) -> Nairobi | F89: John Mwangi | G89: =PROPER(TRIM(F89)) -> John Mwangi | H89: P007 | I89: Mosquito Net - Family Size | J89: =PROPER(TRIM(I89)) -> Mosquito Net - Family Size | K89: 10 | L89: =IF(K89="",0,K89) -> 10 | M89: 600 | N89: =IF(M89="",0,M89) -> 600 | O89: =IF(L89<0,"NEGATIVE QUANTITY","") | P89: =ABS(L89) -> 10 | Q89: =VLOOKUP(H89,'Product Cost Lookup'!A:D,4,FALSE) -> 400 | R89: =VLOOKUP(H89,'Product Cost Lookup'!A:D,3,FALSE) -> Household | S89: =P89*N89 -> 6000 | T89: =P89*Q89 -> 4000 | U89: =S89-T89 -> 2000 | V89: =IF(S89=0,0,U89/S89) -> 0.33333333 | W89: =TEXT(C89,"mmm") -> Feb
A90: 10019 | B90: 45376 | C90: 45376 | D90: Eldoret | E90: =IF(TRIM(D90)="","Unknown",PROPER(TRIM(D90))) -> Eldoret | F90: Mercy Njeri | G90: =PROPER(TRIM(F90)) -> Mercy Njeri | H90: P015 | I90: Water Dispenser Stand | J90: =PROPER(TRIM(I90)) -> Water Dispenser Stand | K90: 5 | L90: =IF(K90="",0,K90) -> 5 | M90: 2300 | N90: =IF(M90="",0,M90) -> 2300 | O90: =IF(L90<0,"NEGATIVE QUANTITY","") | P90: =ABS(L90) -> 5 | Q90: =VLOOKUP(H90,'Product Cost Lookup'!A:D,4,FALSE) -> 1500 | R90: =VLOOKUP(H90,'Product Cost Lookup'!A:D,3,FALSE) -> Household | S90: =P90*N90 -> 11500 | T90: =P90*Q90 -> 7500 | U90: =S90-T90 -> 4000 | V90: =IF(S90=0,0,U90/S90) -> 0.34782609 | W90: =TEXT(C90,"mmm") -> Mar
A91: 10136 | B91: 45378 | C91: 45378 | D91: Mombasa | E91: =IF(TRIM(D91)="","Unknown",PROPER(TRIM(D91))) -> Mombasa | F91: peter otieno | G91: =PROPER(TRIM(F91)) -> Peter Otieno | H91: P010 | I91: Wheelbarrow - Heavy Duty | J91: =PROPER(TRIM(I91)) -> Wheelbarrow - Heavy Duty | K91: 20 | L91: =IF(K91="",0,K91) -> 20 | M91: 5250 | N91: =IF(M91="",0,M91) -> 5250 | O91: =IF(L91<0,"NEGATIVE QUANTITY","") | P91: =ABS(L91) -> 20 | Q91: =VLOOKUP(H91,'Product Cost Lookup'!A:D,4,FALSE) -> 3500 | R91: =VLOOKUP(H91,'Product Cost Lookup'!A:D,3,FALSE) -> Hardware | S91: =P91*N91 -> 105000 | T91: =P91*Q91 -> 70000 | U91: =S91-T91 -> 35000 | V91: =IF(S91=0,0,U91/S91) -> 0.33333333 | W91: =TEXT(C91,"mmm") -> Mar
A92: 10020 | B92: 45304 | C92: 45304 | D92: NAIROBI | E92: =IF(TRIM(D92)="","Unknown",PROPER(TRIM(D92))) -> Nairobi | F92: Faith Wanjiru | G92: =PROPER(TRIM(F92)) -> Faith Wanjiru | H92: P009 | I92: Thermos Flask 1L | J92: =PROPER(TRIM(I92)) -> Thermos Flask 1L | K92: 5 | L92: =IF(K92="",0,K92) -> 5 | M92: 900 | N92: =IF(M92="",0,M92) -> 900 | O92: =IF(L92<0,"NEGATIVE QUANTITY","") | P92: =ABS(L92) -> 5 | Q92: =VLOOKUP(H92,'Product Cost Lookup'!A:D,4,FALSE) -> 550 | R92: =VLOOKUP(H92,'Product Cost Lookup'!A:D,3,FALSE) -> Kitchenware | S92: =P92*N92 -> 4500 | T92: =P92*Q92 -> 2750 | U92: =S92-T92 -> 1750 | V92: =IF(S92=0,0,U92/S92) -> 0.38888889 | W92: =TEXT(C92,"mmm") -> Jan
A93: 10085 | B93: 45359 | C93: 45359 | D93: Mombasa | E93: =IF(TRIM(D93)="","Unknown",PROPER(TRIM(D93))) -> Mombasa | F93: Brian Mutua | G93: =PROPER(TRIM(F93)) -> Brian Mutua | H93: P007 | I93: Mosquito Net - Family Size | J93: =PROPER(TRIM(I93)) -> Mosquito Net - Family Size | K93: 10 | L93: =IF(K93="",0,K93) -> 10 | M93: 650 | N93: =IF(M93="",0,M93) -> 650 | O93: =IF(L93<0,"NEGATIVE QUANTITY","") | P93: =ABS(L93) -> 10 | Q93: =VLOOKUP(H93,'Product Cost Lookup'!A:D,4,FALSE) -> 400 | R93: =VLOOKUP(H93,'Product Cost Lookup'!A:D,3,FALSE) -> Household | S93: =P93*N93 -> 6500 | T93: =P93*Q93 -> 4000 | U93: =S93-T93 -> 2500 | V93: =IF(S93=0,0,U93/S93) -> 0.38461538 | W93: =TEXT(C93,"mmm") -> Mar
A94: 10073 | B94: 45444 | C94: 45444 | D94: Nairobi | E94: =IF(TRIM(D94)="","Unknown",PROPER(TRIM(D94))) -> Nairobi | F94: Samuel Kiptoo | G94: =PROPER(TRIM(F94)) -> Samuel Kiptoo | H94: P008 | I94: USB Wall Charger UC-5 | J94: =PROPER(TRIM(I94)) -> Usb Wall Charger Uc-5 | K94: 2 | L94: =IF(K94="",0,K94) -> 2 | M94: 450 | N94: =IF(M94="",0,M94) -> 450 | O94: =IF(L94<0,"NEGATIVE QUANTITY","") | P94: =ABS(L94) -> 2 | Q94: =VLOOKUP(H94,'Product Cost Lookup'!A:D,4,FALSE) -> 300 | R94: =VLOOKUP(H94,'Product Cost Lookup'!A:D,3,FALSE) -> Electronics | S94: =P94*N94 -> 900 | T94: =P94*Q94 -> 600 | U94: =S94-T94 -> 300 | V94: =IF(S94=0,0,U94/S94) -> 0.33333333 | W94: =TEXT(C94,"mmm") -> Jun
A95: 10149 | B95: 45326 | C95: 45326 | D95: NAKURU | E95: =IF(TRIM(D95)="","Unknown",PROPER(TRIM(D95))) -> Nakuru | F95: John Mwangi | G95: =PROPER(TRIM(F95)) -> John Mwangi | H95: P014 | I95: LED Bulb 9W (Pack of 4) | J95: =PROPER(TRIM(I95)) -> Led Bulb 9W (Pack Of 4) | K95: 2 | L95: =IF(K95="",0,K95) -> 2 | M95: 780 | N95: =IF(M95="",0,M95) -> 780 | O95: =IF(L95<0,"NEGATIVE QUANTITY","") | P95: =ABS(L95) -> 2 | Q95: =VLOOKUP(H95,'Product Cost Lookup'!A:D,4,FALSE) -> 480 | R95: =VLOOKUP(H95,'Product Cost Lookup'!A:D,3,FALSE) -> Electronics | S95: =P95*N95 -> 1560 | T95: =P95*Q95 -> 960 | U95: =S95-T95 -> 600 | V95: =IF(S95=0,0,U95/S95) -> 0.38461538 | W95: =TEXT(C95,"mmm") -> Feb
A96: 10022 | B96: 45353 | C96: 45353 | D96: ELDORET | E96: =IF(TRIM(D96)="","Unknown",PROPER(TRIM(D96))) -> Eldoret | F96: Aisha Hassan | G96: =PROPER(TRIM(F96)) -> Aisha Hassan | H96: P005 | I96: Non-Stick Frying Pan 28cm | J96: =PROPER(TRIM(I96)) -> Non-Stick Frying Pan 28Cm | K96: 1 | L96: =IF(K96="",0,K96) -> 1 | M96: 1050 | N96: =IF(M96="",0,M96) -> 1050 | O96: =IF(L96<0,"NEGATIVE QUANTITY","") | P96: =ABS(L96) -> 1 | Q96: =VLOOKUP(H96,'Product Cost Lookup'!A:D,4,FALSE) -> 700 | R96: =VLOOKUP(H96,'Product Cost Lookup'!A:D,3,FALSE) -> Kitchenware | S96: =P96*N96 -> 1050 | T96: =P96*Q96 -> 700 | U96: =S96-T96 -> 350 | V96: =IF(S96=0,0,U96/S96) -> 0.33333333 | W96: =TEXT(C96,"mmm") -> Mar
A97: 10006 | B97: 45299 | C97: 45299 | D97: Mombasa | E97: =IF(TRIM(D97)="","Unknown",PROPER(TRIM(D97))) -> Mombasa | F97: John Mwangi | G97: =PROPER(TRIM(F97)) -> John Mwangi | H97: P013 | I97: Kitchen Knife Set | J97: =PROPER(TRIM(I97)) -> Kitchen Knife Set | K97: 6 | L97: =IF(K97="",0,K97) -> 6 | M97: 1350 | N97: =IF(M97="",0,M97) -> 1350 | O97: =IF(L97<0,"NEGATIVE QUANTITY","") | P97: =ABS(L97) -> 6 | Q97: =VLOOKUP(H97,'Product Cost Lookup'!A:D,4,FALSE) -> 800 | R97: =VLOOKUP(H97,'Product Cost Lookup'!A:D,3,FALSE) -> Kitchenware | S97: =P97*N97 -> 8100 | T97: =P97*Q97 -> 4800 | U97: =S97-T97 -> 3300 | V97: =IF(S97=0,0,U97/S97) -> 0.40740741 | W97: =TEXT(C97,"mmm") -> Jan
A98: 10314 | B98: 45361 | C98: 45361 | D98: Kisumu | E98: =IF(TRIM(D98)="","Unknown",PROPER(TRIM(D98))) -> Kisumu | F98: Aisha Hassan | G98: =PROPER(TRIM(F98)) -> Aisha Hassan | H98: P003 | I98: Rechargeable Torch RT-10 | J98: =PROPER(TRIM(I98)) -> Rechargeable Torch Rt-10 | K98: 12 | L98: =IF(K98="",0,K98) -> 12 | M98: 950 | N98: =IF(M98="",0,M98) -> 950 | O98: =IF(L98<0,"NEGATIVE QUANTITY","") | P98: =ABS(L98) -> 12 | Q98: =VLOOKUP(H98,'Product Cost Lookup'!A:D,4,FALSE) -> 600 | R98: =VLOOKUP(H98,'Product Cost Lookup'!A:D,3,FALSE) -> Electronics | S98: =P98*N98 -> 11400 | T98: =P98*Q98 -> 7200 | U98: =S98-T98 -> 4200 | V98: =IF(S98=0,0,U98/S98) -> 0.36842105 | W98: =TEXT(C98,"mmm") -> Mar
A99: 10247 | B99: 45357 | C99: 45357 | D99: NAIROBI | E99: =IF(TRIM(D99)="","Unknown",PROPER(TRIM(D99))) -> Nairobi | F99: Grace Achieng | G99: =PROPER(TRIM(F99)) -> Grace Achieng | H99: P015 | I99: Water Dispenser Stand | J99: =PROPER(TRIM(I99)) -> Water Dispenser Stand | K99: 5 | L99: =IF(K99="",0,K99) -> 5 | M99: 2300 | N99: =IF(M99="",0,M99) -> 2300 | O99: =IF(L99<0,"NEGATIVE QUANTITY","") | P99: =ABS(L99) -> 5 | Q99: =VLOOKUP(H99,'Product Cost Lookup'!A:D,4,FALSE) -> 1500 | R99: =VLOOKUP(H99,'Product Cost Lookup'!A:D,3,FALSE) -> Household | S99: =P99*N99 -> 11500 | T99: =P99*Q99 -> 7500 | U99: =S99-T99 -> 4000 | V99: =IF(S99=0,0,U99/S99) -> 0.34782609 | W99: =TEXT(C99,"mmm") -> Mar
A100: 10325 | B100: 45368 | C100: 45368 | D100: Eldoret | E100: =IF(TRIM(D100)="","Unknown",PROPER(TRIM(D100))) -> Eldoret | F100: Peter Otieno | G100: =PROPER(TRIM(F100)) -> Peter Otieno | H100: P002 | I100: solar lantern sl-200 | J100: =PROPER(TRIM(I100)) -> Solar Lantern Sl-200 | K100: 12 | L100: =IF(K100="",0,K100) -> 12 | M100: 1450 | N100: =IF(M100="",0,M100) -> 1450 | O100: =IF(L100<0,"NEGATIVE QUANTITY","") | P100: =ABS(L100) -> 12 | Q100: =VLOOKUP(H100,'Product Cost Lookup'!A:D,4,FALSE) -> 900 | R100: =VLOOKUP(H100,'Product Cost Lookup'!A:D,3,FALSE) -> Electronics | S100: =P100*N100 -> 17400 | T100: =P100*Q100 -> 10800 | U100: =S100-T100 -> 6600 | V100: =IF(S100=0,0,U100/S100) -> 0.37931034 | W100: =TEXT(C100,"mmm") -> Mar
A101: 10283 | B101: 45354 | C101: 45354 | D101: Mombasa | E101: =IF(TRIM(D101)="","Unknown",PROPER(TRIM(D101))) -> Mombasa | F101: Grace Achieng | G101: =PROPER(TRIM(F101)) -> Grace Achieng | H101: P005 | I101: Non-Stick Frying Pan 28cm | J101: =PROPER(TRIM(I101)) -> Non-Stick Frying Pan 28Cm | K101: 6 | L101: =IF(K101="",0,K101) -> 6 | M101: 1100 | N101: =IF(M101="",0,M101) -> 1100 | O101: =IF(L101<0,"NEGATIVE QUANTITY","") | P101: =ABS(L101) -> 6 | Q101: =VLOOKUP(H101,'Product Cost Lookup'!A:D,4,FALSE) -> 700 | R101: =VLOOKUP(H101,'Product Cost Lookup'!A:D,3,FALSE) -> Kitchenware | S101: =P101*N101 -> 6600 | T101: =P101*Q101 -> 4200 | U101: =S101-T101 -> 2400 | V101: =IF(S101=0,0,U101/S101) -> 0.36363636 | W101: =TEXT(C101,"mmm") -> Mar
... A105: 10207 | B105: 45342 | C105: 45342 | D105: NAKURU | E105: =IF(TRIM(D105)="","Unknown",PROPER(TRIM(D105))) -> Nakuru | F105: John Mwangi | G105: =PROPER(TRIM(F105)) -> John Mwangi | H105: P007 | I105: Mosquito Net - Family Size | J105: =PROPER(TRIM(I105)) -> Mosquito Net - Family Size | K105: 20 | L105: =IF(K105="",0,K105) -> 20 | M105: 700 | N105: =IF(M105="",0,M105) -> 700 | O105: =IF(L105<0,"NEGATIVE QUANTITY","") | P105: =ABS(L105) -> 20 | Q105: =VLOOKUP(H105,'Product Cost Lookup'!A:D,4,FALSE) -> 400 | R105: =VLOOKUP(H105,'Product Cost Lookup'!A:D,3,FALSE) -> Household | S105: =P105*N105 -> 14000 | T105: =P105*Q105 -> 8000 | U105: =S105-T105 -> 6000 | V105: =IF(S105=0,0,U105/S105) -> 0.42857143 | W105: =TEXT(C105,"mmm") -> Feb
A106: 10154 | B106: 45371 | C106: 45371 | D106: Thika | E106: =IF(TRIM(D106)="","Unknown",PROPER(TRIM(D106))) -> Thika | F106: Aisha Hassan | G106: =PROPER(TRIM(F106)) -> Aisha Hassan | H106: P011 | I106: Padlock Set (3pc) | J106: =PROPER(TRIM(I106)) -> Padlock Set (3Pc) | L106: =IF(K106="",0,K106) -> 0 | M106: 650 | N106: =IF(M106="",0,M106) -> 650 | O106: =IF(L106<0,"NEGATIVE QUANTITY","") | P106: =ABS(L106) -> 0 | Q106: =VLOOKUP(H106,'Product Cost Lookup'!A:D,4,FALSE) -> 450 | R106: =VLOOKUP(H106,'Product Cost Lookup'!A:D,3,FALSE) -> Hardware | S106: =P106*N106 -> 0 | T106: =P106*Q106 -> 0 | U106: =S106-T106 -> 0 | V106: =IF(S106=0,0,U106/S106) -> 0 | W106: =TEXT(C106,"mmm") -> Mar
A107: 10277 | B107: 45329 | C107: 45329 | D107: Thika | E107: =IF(TRIM(D107)="","Unknown",PROPER(TRIM(D107))) -> Thika | F107: Grace Achieng | G107: =PROPER(TRIM(F107)) -> Grace Achieng | H107: P005 | I107: Non-Stick Frying Pan 28cm | J107: =PROPER(TRIM(I107)) -> Non-Stick Frying Pan 28Cm | K107: 2 | L107: =IF(K107="",0,K107) -> 2 | M107: 1100 | N107: =IF(M107="",0,M107) -> 1100 | O107: =IF(L107<0,"NEGATIVE QUANTITY","") | P107: =ABS(L107) -> 2 | Q107: =VLOOKUP(H107,'Product Cost Lookup'!A:D,4,FALSE) -> 700 | R107: =VLOOKUP(H107,'Product Cost Lookup'!A:D,3,FALSE) -> Kitchenware | S107: =P107*N107 -> 2200 | T107: =P107*Q107 -> 1400 | U107: =S107-T107 -> 800 | V107: =IF(S107=0,0,U107/S107) -> 0.36363636 | W107: =TEXT(C107,"mmm") -> Feb
A108: 10161 | B108: 45340 | C108: 45340 | D108: thika | E108: =IF(TRIM(D108)="","Unknown",PROPER(TRIM(D108))) -> Thika | F108: Peter Otieno | G108: =PROPER(TRIM(F108)) -> Peter Otieno | H108: P012 | I108: Garden Hose 20m | J108: =PROPER(TRIM(I108)) -> Garden Hose 20M | K108: 8 | L108: =IF(K108="",0,K108) -> 8 | M108: 1700 | N108: =IF(M108="",0,M108) -> 1700 | O108: =IF(L108<0,"NEGATIVE QUANTITY","") | P108: =ABS(L108) -> 8 | Q108: =VLOOKUP(H108,'Product Cost Lookup'!A:D,4,FALSE) -> 1100 | R108: =VLOOKUP(H108,'Product Cost Lookup'!A:D,3,FALSE) -> Hardware | S108: =P108*N108 -> 13600 | T108: =P108*Q108 -> 8800 | U108: =S108-T108 -> 4800 | V108: =IF(S108=0,0,U108/S108) -> 0.35294118 | W108: =TEXT(C108,"mmm") -> Feb
A109: 10262 | B109: 45377 | C109: 45377 | D109: Thika | E109: =IF(TRIM(D109)="","Unknown",PROPER(TRIM(D109))) -> Thika | F109: Brian Mutua | G109: =PROPER(TRIM(F109)) -> Brian Mutua | H109: P011 | I109: Padlock Set (3pc) | J109: =PROPER(TRIM(I109)) -> Padlock Set (3Pc) | K109: -12 | L109: =IF(K109="",0,K109) -> -12 | M109: 700 | N109: =IF(M109="",0,M109) -> 700 | O109: =IF(L109<0,"NEGATIVE QUANTITY","") -> NEGATIVE QUANTITY | P109: =ABS(L109) -> 12 | Q109: =VLOOKUP(H109,'Product Cost Lookup'!A:D,4,FALSE) -> 450 | R109: =VLOOKUP(H109,'Product Cost Lookup'!A:D,3,FALSE) -> Hardware | S109: =P109*N109 -> 8400 | T109: =P109*Q109 -> 5400 | U109: =S109-T109 -> 3000 | V109: =IF(S109=0,0,U109/S109) -> 0.35714286 | W109: =TEXT(C109,"mmm") -> Mar
A110: 10082 | B110: 45307 | C110: 45307 | D110: Nakuru | E110: =IF(TRIM(D110)="","Unknown",PROPER(TRIM(D110))) -> Nakuru | F110: Mercy Njeri | G110: =PROPER(TRIM(F110)) -> Mercy Njeri | H110: P014 | I110: LED Bulb 9W (Pack of 4) | J110: =PROPER(TRIM(I110)) -> Led Bulb 9W (Pack Of 4) | K110: 20 | L110: =IF(K110="",0,K110) -> 20 | M110: 830 | N110: =IF(M110="",0,M110) -> 830 | O110: =IF(L110<0,"NEGATIVE QUANTITY","") | P110: =ABS(L110) -> 20 | Q110: =VLOOKUP(H110,'Product Cost Lookup'!A:D,4,FALSE) -> 480 | R110: =VLOOKUP(H110,'Product Cost Lookup'!A:D,3,FALSE) -> Electronics | S110: =P110*N110 -> 16600 | T110: =P110*Q110 -> 9600 | U110: =S110-T110 -> 7000 | V110: =IF(S110=0,0,U110/S110) -> 0.42168675 | W110: =TEXT(C110,"mmm") -> Jan
A111: 10206 | B111: 45294 | C111: 45294 | D111: Nairobi | E111: =IF(TRIM(D111)="","Unknown",PROPER(TRIM(D111))) -> Nairobi | F111: Faith Wanjiru | G111: =PROPER(TRIM(F111)) -> Faith Wanjiru | H111: P015 | I111: Water Dispenser Stand | J111: =PROPER(TRIM(I111)) -> Water Dispenser Stand | K111: 20 | L111: =IF(K111="",0,K111) -> 20 | M111: 2350 | N111: =IF(M111="",0,M111) -> 2350 | O111: =IF(L111<0,"NEGATIVE QUANTITY","") | P111: =ABS(L111) -> 20 | Q111: =VLOOKUP(H111,'Product Cost Lookup'!A:D,4,FALSE) -> 1500 | R111: =VLOOKUP(H111,'Product Cost Lookup'!A:D,3,FALSE) -> Household | S111: =P111*N111 -> 47000 | T111: =P111*Q111 -> 30000 | U111: =S111-T111 -> 17000 | V111: =IF(S111=0,0,U111/S111) -> 0.36170213 | W111: =TEXT(C111,"mmm") -> Jan
A112: 10091 | B112: 45310 | C112: 45310 | D112: Kisumu | E112: =IF(TRIM(D112)="","Unknown",PROPER(TRIM(D112))) -> Kisumu | F112: Faith Wanjiru | G112: =PROPER(TRIM(F112)) -> Faith Wanjiru | H112: P003 | I112: Rechargeable Torch RT-10 | J112: =PROPER(TRIM(I112)) -> Rechargeable Torch Rt-10 | K112: 15 | L112: =IF(K112="",0,K112) -> 15 | M112: 950 | N112: =IF(M112="",0,M112) -> 950 | O112: =IF(L112<0,"NEGATIVE QUANTITY","") | P112: =ABS(L112) -> 15 | Q112: =VLOOKUP(H112,'Product Cost Lookup'!A:D,4,FALSE) -> 600 | R112: =VLOOKUP(H112,'Product Cost Lookup'!A:D,3,FALSE) -> Electronics | S112: =P112*N112 -> 14250 | T112: =P112*Q112 -> 9000 | U112: =S112-T112 -> 5250 | V112: =IF(S112=0,0,U112/S112) -> 0.36842105 | W112: =TEXT(C112,"mmm") -> Jan
...

Sheet Product Cost Lookup
A1: Product ID | B1: Product Name | C1: Category | D1: Unit Cost (KES)
A2: P001 | B2: 20L Jerrycan - Blue | C2: Household | D2: 350
A3: P002 | B3: Solar Lantern SL-200 | C3: Electronics | D3: 900
A4: P003 | B4: Rechargeable Torch RT-10 | C4: Electronics | D4: 600
A5: P004 | B5: Cooking Gas Burner CB-2 | C5: Kitchenware | D5: 1200
A6: P005 | B6: Non-Stick Frying Pan 28cm | C6: Kitchenware | D6: 700
A7: P006 | B7: Plastic Storage Basket L | C7: Household | D7: 250
A8: P007 | B8: Mosquito Net - Family Size | C8: Household | D8: 400
A9: P008 | B9: USB Wall Charger UC-5 | C9: Electronics | D9: 300
A10: P009 | B10: Thermos Flask 1L | C10: Kitchenware | D10: 550
A11: P010 | B11: Wheelbarrow - Heavy Duty | C11: Hardware | D11: 3500
A12: P011 | B12: Padlock Set (3pc) | C12: Hardware | D12: 450
A13: P012 | B13: Garden Hose 20m | C13: Hardware | D13: 1100
... A16: P015 | B16: Water Dispenser Stand | C16: Household | D16: 1500

Sheet PIVOT - REGION
A2: Cleaned Region | B2: Sum of Revenue | C2: Sum of Profit
A3: Eldoret | B3: 580680 | C3: 198620
A4: Kisumu | B4: 619050 | C4: 212600
A5: Mombasa | B5: 636960 | C5: 240700
A6: Nairobi | B6: 710700 | C6: 240850
A7: Nakuru | B7: 425560 | C7: 155820
A8: Thika | B8: 517900 | C8: 184380
A9: Unknown | B9: 80600 | C9: 31050
A10: Grand Total | B10: 3571450 | C10: 1264020
H20: =GETPIVOTDATA("Sum of Profit",'PIVOT - REGION'!$A$3) -> 1264020

Sheet PIVOT - SALES REP
A2: Cleaned Sales Rep | B2: Sum of Revenue | C2: Sum of Profit
A3: Aisha Hassan | B3: 300540 | C3: 90840
A4: Brian Mutua | B4: 445850 | C4: 159380
A5: Faith Wanjiru | B5: 412200 | C5: 149800
A6: Grace Achieng | B6: 474600 | C6: 172100
A7: John Mwangi | B7: 388840 | C7: 139190
A8: Mercy Njeri | B8: 485380 | C8: 169260
A9: Peter Otieno | B9: 503840 | C9: 182400
A10: Samuel Kiptoo | B10: 560200 | C10: 201050
A11: Grand Total | B11: 3571450 | C11: 1264020

Sheet PIVOT - CATEGORY
A2: Category | B2: Sum of Revenue | C2: Sum of Profit
A3: Electronics | B3: 618380 | C3: 230300
A4: Hardware | B4: 1359600 | C4: 454150
A5: Household | B5: 779020 | C5: 281020
A6: Kitchenware | B6: 814450 | C6: 298550
A7: Grand Total | B7: 3571450 | C7: 1264020

Sheet PIVOT - TOP 5 PRODUCTS
A2: Cleaned Product Name | B2: Sum of Revenue
A3: Cooking Gas Burner Cb-2 | B3: 306500
A4: Garden Hose 20M | B4: 540250
A5: Kitchen Knife Set | B5: 290150
A6: Water Dispenser Stand | B6: 456600
A7: Wheelbarrow - Heavy Duty | B7: 459650
A8: Grand Total | B8: 2053150

Sheet PIVOT - MONTH
H7: Month | I7: Sum of Revenue | J7: Sum of Profit
H8: Jan | I8: 982630 | J8: 357600
H9: Feb | I9: 857320 | J9: 319560
H10: Mar | I10: 1288420 | J10: 441280
H11: Apr | I11: 16300 | J11: 6400
H12: May | I12: 54650 | J12: 20150
H13: Jun | I13: 159600 | J13: 41100
H14: Jul | I14: 7650 | J14: 3200
H15: Aug | I15: 77480 | J15: 26180
H16: Sep | I16: 10400 | J16: 3400
H17: Oct | I17: 37900 | J17: 13350
H18: Nov | I18: 28100 | J18: 11300
H19: Dec | I19: 51000 | J19: 20500
H20: Grand Total | I20: 3571450 | J20: 1264020

Sheet Dashboard
J2: Highland Distributors Sales Dashboard
H6: Total Revenue | L6: Total Profit
H7: =GETPIVOTDATA("Sum of Revenue",'PIVOT - REGION'!$A$3) -> 3571450 | L7: =GETPIVOTDATA("Sum of Profit",'PIVOT - REGION'!$A$3) -> 1264020
H10: Avg Margin % | L10: Total Orders
H11: =L7/H7 -> 0.35392348 | L11: =COUNTA('Cleaned Sales Data'!A:A)-1 -> 340
J19: Monthly Revenue Chart
J38: Revenue by Region
J58: Top 5 Products by Revenue
J60: Cleaned Product Name | K60: Sum of Revenue
J61: Cooking Gas Burner Cb-2 | K61: 306500
J62: Garden Hose 20M | K62: 540250
J63: Kitchen Knife Set | K63: 290150
J64: Water Dispenser Stand | K64: 456600
J65: Wheelbarrow - Heavy Duty | K65: 459650
J66: Grand Total | K66: 2053150
J73: Slicers

Sheet Data Cleaning notes
J1: Data Cleaning Notes
H6: Issue | J6: Resolution
H7: Mixed Dates | J7: All dates converted to real excel dates
H8: Missing Regions | J8: Set to "Unkown" and used TRIM
H9: Missing Quantities | J9: Set to 0 and flagged for review
H10: Missing Unit Price | J10: Set to 0 and flagged for review
H11: Negative Quantity | J11: Converted using ABS() and flagged for review
H12: Duplicate Rows | J12: Removed 18 duplicates
H13: Sales Rep Formatting | J13: Standardized using PROPER and TRIM
H14: Region Formatting | J14: Standardized using PROPER and TRIM
H15: Product names | J15: Standardized using TRIM
H16: Unit Cost & Category | J16: Added using VLOOKUP from Product Cost Lookup

Sheet Cleaned_Sales Table
A1: Order ID | B1: Order Date | C1: Cleaned Order Date | D1: Region | E1: Cleaned Region | F1: Sales Rep | G1: Cleaned Sales Rep | H1: Product ID | I1: Product Name | J1: Cleaned Product Name | K1: Quantity | L1: New Quantity | M1: Unit Price (KES) | N1: Cleaned Unit Price (KES) | O1: Flags | P1: Cleaned Quantity | Q1: Unit Cost | R1: Category | S1: Revenue | T1: Cost | U1: Profit | V1: Margin % | W1: Month
A2: 10008 | B2: 45306 | C2: 45306 | D2: mombasa | E2: Mombasa | F2: Peter Otieno | G2: Peter Otieno | H2: P013 | I2: Kitchen Knife Set | J2: Kitchen Knife Set | K2: 20 | L2: 20 | M2: 1350 | N2: 1350 | P2: 20 | Q2: 800 | R2: Kitchenware | S2: 27000 | T2: 16000 | U2: 11000 | V2: 0.40740741 | W2: Jan
A3: 10300 | B3: 45364 | C3: 45364 | D3: nakuru | E3: Nakuru | F3: Faith Wanjiru | G3: Faith Wanjiru | H3: P013 | I3: Kitchen Knife Set | J3: Kitchen Knife Set | K3: 6 | L3: 6 | M3: 1350 | N3: 1350 | P3: 6 | Q3: 800 | R3: Kitchenware | S3: 8100 | T3: 4800 | U3: 3300 | V3: 0.40740741 | W3: Mar
A4: 10328 | B4: 45338 | C4: 45338 | D4: Mombasa | E4: Mombasa | F4: Grace Achieng | G4: Grace Achieng | H4: P001 | I4: 20L Jerrycan - Blue | J4: 20L Jerrycan - Blue | K4: 4 | L4: 4 | M4: 600 | N4: 600 | P4: 4 | Q4: 350 | R4: Household | S4: 2400 | T4: 1400 | U4: 1000 | V4: 0.41666667 | W4: Feb
A5: 10216 | B5: 45373 | C5: 45373 | D5: Eldoret | E5: Eldoret | F5: grace achieng | G5: Grace Achieng | H5: P015 | I5: Water Dispenser Stand | J5: Water Dispenser Stand | K5: 10 | L5: 10 | M5: 2300 | N5: 2300 | P5: 10 | Q5: 1500 | R5: Household | S5: 23000 | T5: 15000 | U5: 8000 | V5: 0.34782609 | W5: Mar
A6: 10065 | B6: 45505 | C6: 45505 | D6: KISUMU | E6: Kisumu | F6: Mercy Njeri | G6: Mercy Njeri | H6: P006 | I6: Plastic Storage Basket L | J6: Plastic Storage Basket L | K6: 8 | L6: 8 | M6: 420 | N6: 420 | P6: 8 | Q6: 250 | R6: Household | S6: 3360 | T6: 2000 | U6: 1360 | V6: 0.4047619 | W6: Aug
A7: 10222 | B7: 45339 | C7: 45339 | D7: Mombasa | E7: Mombasa | F7: aisha hassan | G7: Aisha Hassan | H7: P001 | I7: 20L Jerrycan - Blue | J7: 20L Jerrycan - Blue | K7: 5 | L7: 5 | M7: 600 | N7: 600 | P7: 5 | Q7: 350 | R7: Household | S7: 3000 | T7: 1750 | U7: 1250 | V7: 0.41666667 | W7: Feb
A8: 10140 | B8: 45306 | C8: 45306 | D8: Thika | E8: Thika | F8: Faith Wanjiru | G8: Faith Wanjiru | H8: P012 | I8: Garden Hose 20m | J8: Garden Hose 20M | K8: 15 | L8: 15 | M8: 1750 | N8: 1750 | P8: 15 | Q8: 1100 | R8: Hardware | S8: 26250 | T8: 16500 | U8: 9750 | V8: 0.37142857 | W8: Jan
A9: 10268 | B9: 45336 | C9: 45336 | D9: Mombasa | E9: Mombasa | F9: Faith Wanjiru | G9: Faith Wanjiru | H9: P011 | I9: PADLOCK SET (3PC) | J9: Padlock Set (3Pc) | K9: 6 | L9: 6 | M9: 700 | N9: 700 | P9: 6 | Q9: 450 | R9: Hardware | S9: 4200 | T9: 2700 | U9: 1500 | V9: 0.35714286 | W9: Feb
A10: 10025 | B10: 45323 | C10: 45323 | D10: Kisumu | E10: Kisumu | F10: PETER OTIENO | G10: Peter Otieno | H10: P013 | I10: Kitchen Knife Set | J10: Kitchen Knife Set | K10: 2 | L10: 2 | M10: 1350 | N10: 1350 | P10: 2 | Q10: 800 | R10: Kitchenware | S10: 2700 | T10: 1600 | U10: 1100 | V10: 0.40740741 | W10: Feb
A11: 10205 | B11: 45599 | C11: 45599 | D11: MOMBASA | E11: Mombasa | F11: Grace Achieng | G11: Grace Achieng | H11: P008 | I11: USB Wall Charger UC-5 | J11: Usb Wall Charger Uc-5 | K11: 2 | L11: 2 | M11: 500 | N11: 500 | P11: 2 | Q11: 300 | R11: Electronics | S11: 1000 | T11: 600 | U11: 400 | V11: 0.4 | W11: Nov
A12: 10188 | B12: 45370 | C12: 45370 | D12: Thika | E12: Thika | F12: Peter Otieno | G12: Peter Otieno | H12: P008 | I12: USB Wall Charger UC-5 | J12: Usb Wall Charger Uc-5 | K12: 6 | L12: 6 | M12: 500 | N12: 500 | P12: 6 | Q12: 300 | R12: Electronics | S12: 3000 | T12: 1800 | U12: 1200 | V12: 0.4 | W12: Mar
A13: 10152 | B13: 45321 | C13: 45321 | D13: Nakuru | E13: Nakuru | F13: faith wanjiru | G13: Faith Wanjiru | H13: P008 | I13: USB Wall Charger UC-5 | J13: Usb Wall Charger Uc-5 | K13: 12 | L13: 12 | M13: 500 | N13: 500 | P13: 12 | Q13: 300 | R13: Electronics | S13: 6000 | T13: 3600 | U13: 2400 | V13: 0.4 | W13: Jan
A14: 10137 | B14: 45325 | C14: 45325 | D14: Nakuru | E14: Nakuru | F14: Faith Wanjiru | G14: Faith Wanjiru | H14: P008 | I14: USB Wall Charger UC-5 | J14: Usb Wall Charger Uc-5 | K14: -5 | L14: -5 | M14: 500 | N14: 500 | O14: NEGATIVE QUANTITY | P14: 5 | Q14: 300 | R14: Electronics | S14: 2500 | T14: 1500 | U14: 1000 | V14: 0.4 | W14: Feb
A15: 10107 | B15: 45296 | C15: 45296 | D15: Kisumu | E15: Kisumu | F15: FAITH WANJIRU | G15: Faith Wanjiru | H15: P001 | I15: 20L Jerrycan - Blue | J15: 20L Jerrycan - Blue | K15: 4 | L15: 4 | M15: 500 | N15: 500 | P15: 4 | Q15: 350 | R15: Household | S15: 2000 | T15: 1400 | U15: 600 | V15: 0.3 | W15: Jan
A16: 10067 | B16: 45346 | C16: 45346 | D16: thika | E16: Thika | F16: Samuel Kiptoo | G16: Samuel Kiptoo | H16: P008 | I16: USB Wall Charger UC-5 | J16: Usb Wall Charger Uc-5 | K16: 5 | L16: 5 | M16: 500 | N16: 500 | P16: 5 | Q16: 300 | R16: Electronics | S16: 2500 | T16: 1500 | U16: 1000 | V16: 0.4 | W16: Feb
A17: 10030 | B17: 45445 | C17: 45445 | D17: Mombasa | E17: Mombasa | F17: Brian Mutua | G17: Brian Mutua | H17: P013 | I17: Kitchen Knife Set | J17: Kitchen Knife Set | K17: 15 | L17: 15 | M17: 1400 | N17: 1400 | P17: 15 | Q17: 800 | R17: Kitchenware | S17: 21000 | T17: 12000 | U17: 9000 | V17: 0.42857143 | W17: Jun
A18: 10109 | B18: 45597 | C18: 45597 | D18: thika | E18: Thika | F18: Brian Mutua | G18: Brian Mutua | H18: P002 | I18: Solar Lantern SL200 | J18: Solar Lantern Sl200 | K18: 8 | L18: 8 | M18: 1550 | N18: 1550 | P18: 8 | Q18: 900 | R18: Electronics | S18: 12400 | T18: 7200 | U18: 5200 | V18: 0.41935484 | W18: Nov
A19: 10218 | B19: 45365 | C19: 45365 | D19: Thika | E19: Thika | F19: Faith Wanjiru | G19: Faith Wanjiru | H19: P003 | I19: RECHARGEABLE TORCH RT-10 | J19: Rechargeable Torch Rt-10 | K19: 10 | L19: 10 | M19: 900 | N19: 900 | P19: 10 | Q19: 600 | R19: Electronics | S19: 9000 | T19: 6000 | U19: 3000 | V19: 0.33333333 | W19: Mar
A20: 10228 | B20: 45381 | C20: 45381 | D20: Thika | E20: Thika | F20: Grace Achieng | G20: Grace Achieng | H20: P014 | I20: LED Bulb 9W (Pack of 4) | J20: Led Bulb 9W (Pack Of 4) | K20: 4 | L20: 4 | M20: 780 | N20: 780 | P20: 4 | Q20: 480 | R20: Electronics | S20: 3120 | T20: 1920 | U20: 1200 | V20: 0.38461538 | W20: Mar
A21: 10111 | B21: 21/01/2024 | C21: 45312 | D21: Nairobi | E21: Nairobi | F21: PETER OTIENO | G21: Peter Otieno | H21: P014 | I21: LED Bulb 9W (Pack of 4) | J21: Led Bulb 9W (Pack Of 4) | K21: 15 | L21: 15 | M21: 830 | N21: 830 | P21: 15 | Q21: 480 | R21: Electronics | S21: 12450 | T21: 7200 | U21: 5250 | V21: 0.42168675 | W21: Jan
A22: 10255 | B22: 45446 | C22: 45446 | D22: Eldoret | E22: Eldoret | F22: Faith Wanjiru | G22: Faith Wanjiru | H22: P011 | I22: Padlock Set (3pc) | J22: Padlock Set (3Pc) | K22: 20 | L22: 20 | M22: 750 | N22: 750 | P22: 20 | Q22: 450 | R22: Hardware | S22: 15000 | T22: 9000 | U22: 6000 | V22: 0.4 | W22: Jun
A23: 10236 | B23: 45335 | C23: 45335 | D23: Thika | E23: Thika | F23: Faith Wanjiru | G23: Faith Wanjiru | H23: P011 | I23: PADLOCK SET (3PC) | J23: Padlock Set (3Pc) | K23: 12 | L23: 12 | M23: 750 | N23: 750 | P23: 12 | Q23: 450 | R23: Hardware | S23: 9000 | T23: 5400 | U23: 3600 | V23: 0.4 | W23: Feb
A24: 10055 | B24: 45378 | C24: 45378 | D24: Kisumu | E24: Kisumu | F24: John Mwangi | G24: John Mwangi | H24: P013 | I24: Kitchen Knife Set | J24: Kitchen Knife Set | K24: 3 | L24: 3 | M24: 1350 | N24: 1350 | P24: 3 | Q24: 800 | R24: Kitchenware | S24: 4050 | T24: 2400 | U24: 1650 | V24: 0.40740741 | W24: Mar
A25: 10090 | B25: 45335 | C25: 45335 | D25: Mombasa | E25: Mombasa | F25: Mercy Njeri | G25: Mercy Njeri | H25: P013 | I25: Kitchen Knife Set | J25: Kitchen Knife Set | K25: 3 | L25: 3 | M25: 1250 | N25: 1250 | P25: 3 | Q25: 800 | R25: Kitchenware | S25: 3750 | T25: 2400 | U25: 1350 | V25: 0.36 | W25: Feb
A26: 10197 | B26: 45338 | C26: 45338 | D26: NAKURU | E26: Nakuru | F26: Peter Otieno | G26: Peter Otieno | H26: P003 | I26: RECHARGEABLE TORCH RT-10 | J26: Rechargeable Torch Rt-10 | K26: 1 | L26: 1 | M26: 1050 | N26: 1050 | P26: 1 | Q26: 600 | R26: Electronics | S26: 1050 | T26: 600 | U26: 450 | V26: 0.42857143 | W26: Feb
A27: 10242 | B27: 45368 | C27: 45368 | E27: Unknown | F27: MERCY NJERI | G27: Mercy Njeri | H27: P007 | I27: MOSQUITO NET - FAMILY SIZE | J27: Mosquito Net - Family Size | K27: 20 | L27: 20 | M27: 650 | N27: 650 | P27: 20 | Q27: 400 | R27: Household | S27: 13000 | T27: 8000 | U27: 5000 | V27: 0.38461538 | W27: Mar
A28: 10289 | B28: 18/02/2024 | C28: 45340 | D28: Nakuru | E28: Nakuru | F28: Peter Otieno | G28: Peter Otieno | H28: P002 | I28: Solar Lantern SL-200 | J28: Solar Lantern Sl-200 | K28: 1 | L28: 1 | M28: 1450 | N28: 1450 | P28: 1 | Q28: 900 | R28: Electronics | S28: 1450 | T28: 900 | U28: 550 | V28: 0.37931034 | W28: Feb
A29: 10108 | B29: 45375 | C29: 45375 | D29: KISUMU | E29: Kisumu | F29: Samuel Kiptoo | G29: Samuel Kiptoo | H29: P002 | I29: solar lantern sl-200 | J29: Solar Lantern Sl-200 | K29: 6 | L29: 6 | M29: 1500 | N29: 1500 | P29: 6 | Q29: 900 | R29: Electronics | S29: 9000 | T29: 5400 | U29: 3600 | V29: 0.4 | W29: Mar
A30: 10087 | B30: 45342 | C30: 45342 | E30: Unknown | F30: John Mwangi | G30: John Mwangi | H30: P001 | I30: 20L Jerrycan - Blue | J30: 20L Jerrycan - Blue | K30: 4 | L30: 4 | M30: 550 | N30: 550 | P30: 4 | Q30: 350 | R30: Household | S30: 2200 | T30: 1400 | U30: 800 | V30: 0.36363636 | W30: Feb
A31: 10263 | B31: 45328 | C31: 45328 | D31: Thika | E31: Thika | F31: Samuel Kiptoo | G31: Samuel Kiptoo | H31: P003 | I31: Rechargeable Torch RT-10 | J31: Rechargeable Torch Rt-10 | K31: 1 | L31: 1 | M31: 950 | N31: 950 | P31: 1 | Q31: 600 | R31: Electronics | S31: 950 | T31: 600 | U31: 350 | V31: 0.36842105 | W31: Feb
A32: 10038 | B32: 45376 | C32: 45376 | D32: Nairobi | E32: Nairobi | F32: Grace Achieng | G32: Grace Achieng | H32: P011 | I32: Padlock Set (3pc) | J32: Padlock Set (3Pc) | K32: 8 | L32: 8 | M32: 700 | N32: 700 | P32: 8 | Q32: 450 | R32: Hardware | S32: 5600 | T32: 3600 | U32: 2000 | V32: 0.35714286 | W32: Mar
A33: 10148 | B33: 45299 | C33: 45299 | D33: Eldoret | E33: Eldoret | F33: Brian Mutua | G33: Brian Mutua | H33: P007 | I33: Mosquito Net - Family Size | J33: Mosquito Net - Family Size | K33: 12 | L33: 12 | M33: 750 | N33: 750 | P33: 12 | Q33: 400 | R33: Household | S33: 9000 | T33: 4800 | U33: 4200 | V33: 0.46666667 | W33: Jan
A34: 10180 | B34: 45382 | C34: 45382 | D34: Eldoret | E34: Eldoret | F34: Brian Mutua | G34: Brian Mutua | H34: P003 | I34: Rechargeable Torch RT-10 | J34: Rechargeable Torch Rt-10 | K34: 15 | L34: 15 | M34: 950 | N34: 950 | P34: 15 | Q34: 600 | R34: Electronics | S34: 14250 | T34: 9000 | U34: 5250 | V34: 0.36842105 | W34: Mar
A35: 10027 | B35: 45296 | C35: 45296 | D35: Nairobi | E35: Nairobi | F35: Brian Mutua | G35: Brian Mutua | H35: P006 | I35: plastic storage basket l | J35: Plastic Storage Basket L | K35: 6 | L35: 6 | M35: 470 | N35: 470 | P35: 6 | Q35: 250 | R35: Household | S35: 2820 | T35: 1500 | U35: 1320 | V35: 0.46808511 | W35: Jan
A36: 10276 | B36: 45310 | C36: 45310 | D36: Mombasa | E36: Mombasa | F36: Peter Otieno | G36: Peter Otieno | H36: P004 | I36: Cooking Gas Burner CB-2 | J36: Cooking Gas Burner Cb-2 | K36: 15 | L36: 15 | M36: 1850 | N36: 1850 | P36: 15 | Q36: 1200 | R36: Kitchenware | S36: 27750 | T36: 18000 | U36: 9750 | V36: 0.35135135 | W36: Jan
A37: 10184 | B37: 45308 | C37: 45308 | D37: ELDORET | E37: Eldoret | F37: Aisha Hassan | G37: Aisha Hassan | H37: P013 | I37: Kitchen Knife Set | J37: Kitchen Knife Set | K37: 6 | L37: 6 | M37: 1250 | N37: 1250 | P37: 6 | Q37: 800 | R37: Kitchenware | S37: 7500 | T37: 4800 | U37: 2700 | V37: 0.36 | W37: Jan
A38: 10062 | B38: 45375 | C38: 45375 | D38: Mombasa | E38: Mombasa | F38: Aisha Hassan | G38: Aisha Hassan | H38: P001 | I38: 20L Jerrycan - Blue | J38: 20L Jerrycan - Blue | K38: 3 | L38: 3 | M38: 650 | N38: 650 | P38: 3 | Q38: 350 | R38: Household | S38: 1950 | T38: 1050 | U38: 900 | V38: 0.46153846 | W38: Mar
A39: 10296 | B39: 45375 | C39: 45375 | D39: ELDORET | E39: Eldoret | F39: Samuel Kiptoo | G39: Samuel Kiptoo | H39: P012 | I39: Garden Hose 20m | J39: Garden Hose 20M | K39: 15 | L39: 15 | M39: 1650 | N39: 1650 | P39: 15 | Q39: 1100 | R39: Hardware | S39: 24750 | T39: 16500 | U39: 8250 | V39: 0.33333333 | W39: Mar
A40: 10186 | B40: 45303 | C40: 45303 | D40: Thika | E40: Thika | F40: Grace Achieng | G40: Grace Achieng | H40: P001 | I40: 20L Jerrycan - Blue | J40: 20L Jerrycan - Blue | K40: 4 | L40: 4 | M40: 600 | N40: 600 | P40: 4 | Q40: 350 | R40: Household | S40: 2400 | T40: 1400 | U40: 1000 | V40: 0.41666667 | W40: Jan
A41: 10311 | B41: 45332 | C41: 45332 | D41: Thika | E41: Thika | F41: Samuel Kiptoo | G41: Samuel Kiptoo | H41: P012 | I41: Garden Hose 20m | J41: Garden Hose 20M | K41: 5 | L41: 5 | M41: 1800 | N41: 1800 | P41: 5 | Q41: 1100 | R41: Hardware | S41: 9000 | T41: 5500 | U41: 3500 | V41: 0.38888889 | W41: Feb
A42: 10170 | B42: 45336 | C42: 45336 | D42: Nairobi | E42: Nairobi | F42: AISHA HASSAN | G42: Aisha Hassan | H42: P002 | I42: solar lantern sl-200 | J42: Solar Lantern Sl-200 | K42: 5 | L42: 5 | M42: 1500 | N42: 1500 | P42: 5 | Q42: 900 | R42: Electronics | S42: 7500 | T42: 4500 | U42: 3000 | V42: 0.4 | W42: Feb
... A46: 10284 | B46: 45358 | C46: 45358 | D46: Thika | E46: Thika | F46: samuel kiptoo | G46: Samuel Kiptoo | H46: P014 | I46: LED Bulb 9W (Pack of 4) | J46: Led Bulb 9W (Pack Of 4) | K46: 5 | L46: 5 | M46: 880 | N46: 880 | P46: 5 | Q46: 480 | R46: Electronics | S46: 4400 | T46: 2400 | U46: 2000 | V46: 0.45454545 | W46: Mar
A47: 10125 | B47: 18/01/2024 | C47: 45309 | D47: Thika | E47: Thika | F47: Mercy Njeri | G47: Mercy Njeri | H47: P013 | I47: Kitchen Knife Set | J47: Kitchen Knife Set | K47: 10 | L47: 10 | M47: 1400 | N47: 1400 | P47: 10 | Q47: 800 | R47: Kitchenware | S47: 14000 | T47: 8000 | U47: 6000 | V47: 0.42857143 | W47: Jan
A48: 10173 | B48: 45367 | C48: 45367 | D48: Nakuru | E48: Nakuru | F48: Brian Mutua | G48: Brian Mutua | H48: P001 | I48: 20L Jerrycan - Blue | J48: 20L Jerrycan - Blue | K48: 4 | L48: 4 | M48: 550 | N48: 550 | P48: 4 | Q48: 350 | R48: Household | S48: 2200 | T48: 1400 | U48: 800 | V48: 0.36363636 | W48: Mar
A49: 10312 | B49: 45294 | C49: 45294 | D49: Mombasa | E49: Mombasa | F49: Faith Wanjiru | G49: Faith Wanjiru | H49: P011 | I49: Padlock Set (3pc) | J49: Padlock Set (3Pc) | K49: 5 | L49: 5 | M49: 650 | N49: 650 | P49: 5 | Q49: 450 | R49: Hardware | S49: 3250 | T49: 2250 | U49: 1000 | V49: 0.30769231 | W49: Jan
A50: 10115 | B50: 45599 | C50: 45599 | D50: Mombasa | E50: Mombasa | F50: grace achieng | G50: Grace Achieng | H50: P002 | I50: SOLAR LANTERN SL-200 | J50: Solar Lantern Sl-200 | K50: 5 | L50: 5 | M50: 1500 | N50: 1500 | P50: 5 | Q50: 900 | R50: Electronics | S50: 7500 | T50: 4500 | U50: 3000 | V50: 0.4 | W50: Nov
A51: 10291 | B51: 45353 | C51: 45353 | D51: Nakuru | E51: Nakuru | F51: Mercy Njeri | G51: Mercy Njeri | H51: P010 | I51: Wheelbarrow Heavy Duty | J51: Wheelbarrow Heavy Duty | K51: 15 | L51: 15 | M51: 5150 | N51: 5150 | P51: 15 | Q51: 3500 | R51: Hardware | S51: 77250 | T51: 52500 | U51: 24750 | V51: 0.32038835 | W51: Mar
A52: 10234 | B52: 45376 | C52: 45376 | D52: kisumu | E52: Kisumu | F52: Samuel Kiptoo | G52: Samuel Kiptoo | H52: P005 | I52: Non-Stick Frying Pan 28cm | J52: Non-Stick Frying Pan 28Cm | K52: 20 | L52: 20 | M52: 1050 | N52: 1050 | P52: 20 | Q52: 700 | R52: Kitchenware | S52: 21000 | T52: 14000 | U52: 7000 | V52: 0.33333333 | W52: Mar
A53: 10335 | B53: 45374 | C53: 45374 | D53: Kisumu | E53: Kisumu | F53: John Mwangi | G53: John Mwangi | H53: P012 | I53: Garden Hose 20m | J53: Garden Hose 20M | K53: 15 | L53: 15 | M53: 1750 | N53: 1750 | P53: 15 | Q53: 1100 | R53: Hardware | S53: 26250 | T53: 16500 | U53: 9750 | V53: 0.37142857 | W53: Mar
A54: 10041 | B54: 45312 | C54: 45312 | D54: Kisumu | E54: Kisumu | F54: Grace Achieng | G54: Grace Achieng | H54: P010 | I54: Wheelbarrow - Heavy Duty | J54: Wheelbarrow - Heavy Duty | K54: 1 | L54: 1 | M54: 5200 | N54: 5200 | P54: 1 | Q54: 3500 | R54: Hardware | S54: 5200 | T54: 3500 | U54: 1700 | V54: 0.32692308 | W54: Jan
A55: 10093 | B55: 45445 | C55: 45445 | D55: Nairobi | E55: Nairobi | F55: Grace Achieng | G55: Grace Achieng | H55: P010 | I55: Wheelbarrow - Heavy Duty | J55: Wheelbarrow - Heavy Duty | K55: 15 | L55: 15 | M55: 5300 | N55: 5300 | P55: 15 | Q55: 3500 | R55: Hardware | S55: 79500 | T55: 52500 | U55: 27000 | V55: 0.33962264 | W55: Jun
A56: 10018 | B56: 45446 | C56: 45446 | D56: Nairobi | E56: Nairobi | F56: Peter Otieno | G56: Peter Otieno | H56: P002 | I56: SOLAR LANTERN SL-200 | J56: Solar Lantern Sl-200 | K56: 15 | L56: 15 | M56: 1400 | N56: 1400 | P56: 15 | Q56: 900 | R56: Electronics | S56: 21000 | T56: 13500 | U56: 7500 | V56: 0.35714286 | W56: Jun
A57: 10209 | B57: 45337 | C57: 45337 | E57: Unknown | F57: Aisha Hassan | G57: Aisha Hassan | H57: P006 | I57: Plastic Storage Basket (L) | J57: Plastic Storage Basket (L) | K57: 15 | L57: 15 | M57: 520 | N57: 520 | P57: 15 | Q57: 250 | R57: Household | S57: 7800 | T57: 3750 | U57: 4050 | V57: 0.51923077 | W57: Feb
A58: 10298 | B58: 45358 | C58: 45358 | D58: nairobi | E58: Nairobi | F58: Grace Achieng | G58: Grace Achieng | H58: P015 | I58: Water Dispenser Stand | J58: Water Dispenser Stand | K58: 2 | L58: 2 | M58: 2400 | N58: 2400 | P58: 2 | Q58: 1500 | R58: Household | S58: 4800 | T58: 3000 | U58: 1800 | V58: 0.375 | W58: Mar
A59: 10080 | B59: 45356 | C59: 45356 | D59: eldoret | E59: Eldoret | F59: Brian Mutua | G59: Brian Mutua | H59: P002 | I59: solar lantern sl-200 | J59: Solar Lantern Sl-200 | K59: 2 | L59: 2 | M59: 1550 | N59: 1550 | P59: 2 | Q59: 900 | R59: Electronics | S59: 3100 | T59: 1800 | U59: 1300 | V59: 0.41935484 | W59: Mar
A60: 10099 | B60: 45378 | C60: 45378 | D60: Thika | E60: Thika | F60: Faith Wanjiru | G60: Faith Wanjiru | H60: P008 | I60: USB Wall Charger UC-5 | J60: Usb Wall Charger Uc-5 | K60: 15 | L60: 15 | M60: 500 | N60: 500 | P60: 15 | Q60: 300 | R60: Electronics | S60: 7500 | T60: 4500 | U60: 3000 | V60: 0.4 | W60: Mar
A61: 10012 | B61: 45319 | C61: 45319 | D61: Eldoret | E61: Eldoret | F61: faith wanjiru | G61: Faith Wanjiru | H61: P012 | I61: Garden Hose 20m | J61: Garden Hose 20M | K61: 5 | L61: 5 | M61: 1750 | N61: 1750 | P61: 5 | Q61: 1100 | R61: Hardware | S61: 8750 | T61: 5500 | U61: 3250 | V61: 0.37142857 | W61: Jan
A62: 10246 | B62: 45312 | C62: 45312 | D62: Nairobi | E62: Nairobi | F62: Aisha Hassan | G62: Aisha Hassan | H62: P015 | I62: WATER DISPENSER STAND | J62: Water Dispenser Stand | K62: 4 | L62: 4 | N62: 0 | P62: 4 | Q62: 1500 | R62: Household | S62: 0 | T62: 6000 | U62: -6000 | V62: 0 | W62: Jan
A63: 10097 | B63: 45374 | C63: 45374 | D63: kisumu | E63: Kisumu | F63: Peter Otieno | G63: Peter Otieno | H63: P011 | I63: Padlock Set (3pc) | J63: Padlock Set (3Pc) | K63: 20 | L63: 20 | M63: 800 | N63: 800 | P63: 20 | Q63: 450 | R63: Hardware | S63: 16000 | T63: 9000 | U63: 7000 | V63: 0.4375 | W63: Mar
A64: 10337 | B64: 45303 | C64: 45303 | D64: Mombasa | E64: Mombasa | F64: Brian Mutua | G64: Brian Mutua | H64: P005 | I64: Non-Stick Frying Pan 28cm | J64: Non-Stick Frying Pan 28Cm | K64: 8 | L64: 8 | M64: 1100 | N64: 1100 | P64: 8 | Q64: 700 | R64: Kitchenware | S64: 8800 | T64: 5600 | U64: 3200 | V64: 0.36363636 | W64: Jan
A65: 10330 | B65: 45372 | C65: 45372 | D65: Mombasa | E65: Mombasa | F65: Brian Mutua | G65: Brian Mutua | H65: P012 | I65: Garden Hose 20m | J65: Garden Hose 20M | K65: 2 | L65: 2 | M65: 1800 | N65: 1800 | P65: 2 | Q65: 1100 | R65: Hardware | S65: 3600 | T65: 2200 | U65: 1400 | V65: 0.38888889 | W65: Mar
A66: 10151 | B66: 45332 | C66: 45332 | D66: Mombasa | E66: Mombasa | F66: Mercy Njeri | G66: Mercy Njeri | H66: P006 | I66: Plastic Storage Basket (L) | J66: Plastic Storage Basket (L) | K66: 8 | L66: 8 | M66: 370 | N66: 370 | P66: 8 | Q66: 250 | R66: Household | S66: 2960 | T66: 2000 | U66: 960 | V66: 0.32432432 | W66: Feb
A67: 10264 | B67: 45322 | C67: 45322 | D67: Eldoret | E67: Eldoret | F67: Samuel Kiptoo | G67: Samuel Kiptoo | H67: P012 | I67: Garden Hose 20m | J67: Garden Hose 20M | K67: 20 | L67: 20 | M67: 1650 | N67: 1650 | P67: 20 | Q67: 1100 | R67: Hardware | S67: 33000 | T67: 22000 | U67: 11000 | V67: 0.33333333 | W67: Jan
A68: 10280 | B68: 45353 | C68: 45353 | D68: Thika | E68: Thika | F68: Grace Achieng | G68: Grace Achieng | H68: P012 | I68: Garden Hose 20m | J68: Garden Hose 20M | K68: 2 | L68: 2 | M68: 1650 | N68: 1650 | P68: 2 | Q68: 1100 | R68: Hardware | S68: 3300 | T68: 2200 | U68: 1100 | V68: 0.33333333 | W68: Mar
A69: 10072 | B69: 14/01/2024 | C69: 45305 | D69: Thika | E69: Thika | F69: Faith Wanjiru | G69: Faith Wanjiru | H69: P008 | I69: USB Wall Charger UC-5 | J69: Usb Wall Charger Uc-5 | K69: 1 | L69: 1 | M69: 600 | N69: 600 | P69: 1 | Q69: 300 | R69: Electronics | S69: 600 | T69: 300 | U69: 300 | V69: 0.5 | W69: Jan
A70: 10077 | B70: 45376 | C70: 45376 | D70: Nairobi | E70: Nairobi | F70: Peter Otieno | G70: Peter Otieno | H70: P001 | I70: 20L Jerrycan - Blue | J70: 20L Jerrycan - Blue | K70: 6 | L70: 6 | N70: 0 | P70: 6 | Q70: 350 | R70: Household | S70: 0 | T70: 2100 | U70: -2100 | V70: 0 | W70: Mar
A71: 10201 | B71: 19/01/2024 | C71: 45310 | D71: Thika | E71: Thika | F71: SAMUEL KIPTOO | G71: Samuel Kiptoo | H71: P002 | I71: SOLAR LANTERN SL-200 | J71: Solar Lantern Sl-200 | K71: 1 | L71: 1 | M71: 1450 | N71: 1450 | P71: 1 | Q71: 900 | R71: Electronics | S71: 1450 | T71: 900 | U71: 550 | V71: 0.37931034 | W71: Jan
A72: 10204 | B72: 45379 | C72: 45379 | D72: Kisumu | E72: Kisumu | F72: JOHN MWANGI | G72: John Mwangi | H72: P004 | I72: Cooking Gas Burner CB-2 | J72: Cooking Gas Burner Cb-2 | K72: 6 | L72: 6 | M72: 1850 | N72: 1850 | P72: 6 | Q72: 1200 | R72: Kitchenware | S72: 11100 | T72: 7200 | U72: 3900 | V72: 0.35135135 | W72: Mar
A73: 10176 | B73: 45373 | C73: 45373 | D73: Eldoret | E73: Eldoret | F73: Peter Otieno | G73: Peter Otieno | H73: P009 | I73: Thermos Flask 1L | J73: Thermos Flask 1L | K73: 3 | L73: 3 | M73: 950 | N73: 950 | P73: 3 | Q73: 550 | R73: Kitchenware | S73: 2850 | T73: 1650 | U73: 1200 | V73: 0.42105263 | W73: Mar
A74: 10059 | B74: 45329 | C74: 45329 | D74: Eldoret | E74: Eldoret | F74: Samuel Kiptoo | G74: Samuel Kiptoo | H74: P007 | I74: Mosquito Net - Family Size | J74: Mosquito Net - Family Size | K74: 10 | L74: 10 | M74: 700 | N74: 700 | P74: 10 | Q74: 400 | R74: Household | S74: 7000 | T74: 4000 | U74: 3000 | V74: 0.42857143 | W74: Feb
A75: 10002 | B75: 45295 | C75: 45295 | D75: Eldoret | E75: Eldoret | F75: Faith Wanjiru | G75: Faith Wanjiru | H75: P012 | I75: Garden Hose 20m | J75: Garden Hose 20M | K75: 20 | L75: 20 | M75: 1800 | N75: 1800 | P75: 20 | Q75: 1100 | R75: Hardware | S75: 36000 | T75: 22000 | U75: 14000 | V75: 0.38888889 | W75: Jan
A76: 10189 | B76: 14/02/2024 | C76: 45336 | D76: Nakuru | E76: Nakuru | F76: Mercy Njeri | G76: Mercy Njeri | H76: P013 | I76: Kitchen Knife Set | J76: Kitchen Knife Set | K76: 3 | L76: 3 | M76: 1300 | N76: 1300 | P76: 3 | Q76: 800 | R76: Kitchenware | S76: 3900 | T76: 2400 | U76: 1500 | V76: 0.38461538 | W76: Feb
A77: 10001 | B77: 45373 | C77: 45373 | D77: Nairobi | E77: Nairobi | F77: John Mwangi | G77: John Mwangi | H77: P012 | I77: Garden Hose 20m | J77: Garden Hose 20M | K77: 5 | L77: 5 | M77: 1700 | N77: 1700 | P77: 5 | Q77: 1100 | R77: Hardware | S77: 8500 | T77: 5500 | U77: 3000 | V77: 0.35294118 | W77: Mar
A78: 10026 | B78: 45327 | C78: 45327 | D78: Nairobi | E78: Nairobi | F78: Samuel Kiptoo | G78: Samuel Kiptoo | H78: P006 | I78: Plastic Storage Basket (L) | J78: Plastic Storage Basket (L) | K78: 20 | L78: 20 | M78: 520 | N78: 520 | P78: 20 | Q78: 250 | R78: Household | S78: 10400 | T78: 5000 | U78: 5400 | V78: 0.51923077 | W78: Feb
A79: 10281 | B79: 45352 | C79: 45352 | D79: Thika | E79: Thika | F79: Peter Otieno | G79: Peter Otieno | H79: P006 | I79: Plastic Storage Basket L | J79: Plastic Storage Basket L | K79: 8 | L79: 8 | M79: 420 | N79: 420 | P79: 8 | Q79: 250 | R79: Household | S79: 3360 | T79: 2000 | U79: 1360 | V79: 0.4047619 | W79: Mar
A80: 10145 | B80: 45444 | C80: 45444 | D80: Nakuru | E80: Nakuru | F80: Aisha Hassan | G80: Aisha Hassan | H80: P004 | I80: Cooking Gas Burner CB-2 | J80: Cooking Gas Burner Cb-2 | K80: 12 | L80: 12 | M80: 1850 | N80: 1850 | P80: 12 | Q80: 1200 | R80: Kitchenware | S80: 22200 | T80: 14400 | U80: 7800 | V80: 0.35135135 | W80: Jun
A81: 10141 | B81: 45294 | C81: 45294 | D81: Nakuru | E81: Nakuru | F81: Samuel Kiptoo | G81: Samuel Kiptoo | H81: P014 | I81: LED Bulb 9W (Pack of 4) | J81: Led Bulb 9W (Pack Of 4) | K81: 1 | L81: 1 | M81: 780 | N81: 780 | P81: 1 | Q81: 480 | R81: Electronics | S81: 780 | T81: 480 | U81: 300 | V81: 0.38461538 | W81: Jan
A82: 10179 | B82: 45346 | C82: 45346 | D82: Nairobi | E82: Nairobi | F82: Faith Wanjiru | G82: Faith Wanjiru | H82: P005 | I82: Non-Stick Frying Pan 28cm | J82: Non-Stick Frying Pan 28Cm | K82: 1 | L82: 1 | M82: 1150 | N82: 1150 | P82: 1 | Q82: 700 | R82: Kitchenware | S82: 1150 | T82: 700 | U82: 450 | V82: 0.39130435 | W82: Feb
A83: 10295 | B83: 45474 | C83: 45474 | D83: mombasa | E83: Mombasa | F83: Brian Mutua | G83: Brian Mutua | H83: P011 | I83: Padlock Set (3pc) | J83: Padlock Set (3Pc) | K83: 1 | L83: 1 | M83: 650 | N83: 650 | P83: 1 | Q83: 450 | R83: Hardware | S83: 650 | T83: 450 | U83: 200 | V83: 0.30769231 | W83: Jul
A84: 10112 | B84: 45301 | C84: 45301 | D84: ELDORET | E84: Eldoret | F84: Peter Otieno | G84: Peter Otieno | H84: P009 | I84: Thermos Flask 1L | J84: Thermos Flask 1L | K84: 6 | L84: 6 | M84: 950 | N84: 950 | P84: 6 | Q84: 550 | R84: Kitchenware | S84: 5700 | T84: 3300 | U84: 2400 | V84: 0.42105263 | W84: Jan
A85: 10086 | B85: 45302 | C85: 45302 | D85: Kisumu | E85: Kisumu | F85: Aisha Hassan | G85: Aisha Hassan | H85: P011 | I85: Padlock Set (3pc) | J85: Padlock Set (3Pc) | K85: 8 | L85: 8 | M85: 750 | N85: 750 | P85: 8 | Q85: 450 | R85: Hardware | S85: 6000 | T85: 3600 | U85: 2400 | V85: 0.4 | W85: Jan
A86: 10040 | B86: 20/01/2024 | C86: 45311 | D86: Mombasa | E86: Mombasa | F86: Peter Otieno | G86: Peter Otieno | H86: P008 | I86: USB WALL CHARGER UC-5 | J86: Usb Wall Charger Uc-5 | K86: 20 | L86: 20 | M86: 450 | N86: 450 | P86: 20 | Q86: 300 | R86: Electronics | S86: 9000 | T86: 6000 | U86: 3000 | V86: 0.33333333 | W86: Jan
A87: 10054 | B87: 45326 | C87: 45326 | D87: Eldoret | E87: Eldoret | F87: Aisha Hassan | G87: Aisha Hassan | H87: P008 | I87: USB Wall Charger UC-5 | J87: Usb Wall Charger Uc-5 | K87: 2 | L87: 2 | M87: 600 | N87: 600 | P87: 2 | Q87: 300 | R87: Electronics | S87: 1200 | T87: 600 | U87: 600 | V87: 0.5 | W87: Feb
A88: 10133 | B88: 45344 | C88: 45344 | D88: Thika | E88: Thika | F88: Aisha Hassan | G88: Aisha Hassan | H88: P008 | I88: USB Wall Charger UC-5 | J88: Usb Wall Charger Uc-5 | K88: 20 | L88: 20 | M88: 500 | N88: 500 | P88: 20 | Q88: 300 | R88: Electronics | S88: 10000 | T88: 6000 | U88: 4000 | V88: 0.4 | W88: Feb
A89: 10105 | B89: 16/02/2024 | C89: 45338 | D89: Nairobi | E89: Nairobi | F89: John Mwangi | G89: John Mwangi | H89: P007 | I89: Mosquito Net - Family Size | J89: Mosquito Net - Family Size | K89: 10 | L89: 10 | M89: 600 | N89: 600 | P89: 10 | Q89: 400 | R89: Household | S89: 6000 | T89: 4000 | U89: 2000 | V89: 0.33333333 | W89: Feb
A90: 10019 | B90: 45376 | C90: 45376 | D90: Eldoret | E90: Eldoret | F90: Mercy Njeri | G90: Mercy Njeri | H90: P015 | I90: Water Dispenser Stand | J90: Water Dispenser Stand | K90: 5 | L90: 5 | M90: 2300 | N90: 2300 | P90: 5 | Q90: 1500 | R90: Household | S90: 11500 | T90: 7500 | U90: 4000 | V90: 0.34782609 | W90: Mar
A91: 10136 | B91: 45378 | C91: 45378 | D91: Mombasa | E91: Mombasa | F91: peter otieno | G91: Peter Otieno | H91: P010 | I91: Wheelbarrow - Heavy Duty | J91: Wheelbarrow - Heavy Duty | K91: 20 | L91: 20 | M91: 5250 | N91: 5250 | P91: 20 | Q91: 3500 | R91: Hardware | S91: 105000 | T91: 70000 | U91: 35000 | V91: 0.33333333 | W91: Mar
A92: 10020 | B92: 45304 | C92: 45304 | D92: NAIROBI | E92: Nairobi | F92: Faith Wanjiru | G92: Faith Wanjiru | H92: P009 | I92: Thermos Flask 1L | J92: Thermos Flask 1L | K92: 5 | L92: 5 | M92: 900 | N92: 900 | P92: 5 | Q92: 550 | R92: Kitchenware | S92: 4500 | T92: 2750 | U92: 1750 | V92: 0.38888889 | W92: Jan
A93: 10085 | B93: 45359 | C93: 45359 | D93: Mombasa | E93: Mombasa | F93: Brian Mutua | G93: Brian Mutua | H93: P007 | I93: Mosquito Net - Family Size | J93: Mosquito Net - Family Size | K93: 10 | L93: 10 | M93: 650 | N93: 650 | P93: 10 | Q93: 400 | R93: Household | S93: 6500 | T93: 4000 | U93: 2500 | V93: 0.38461538 | W93: Mar
A94: 10073 | B94: 45444 | C94: 45444 | D94: Nairobi | E94: Nairobi | F94: Samuel Kiptoo | G94: Samuel Kiptoo | H94: P008 | I94: USB Wall Charger UC-5 | J94: Usb Wall Charger Uc-5 | K94: 2 | L94: 2 | M94: 450 | N94: 450 | P94: 2 | Q94: 300 | R94: Electronics | S94: 900 | T94: 600 | U94: 300 | V94: 0.33333333 | W94: Jun
A95: 10149 | B95: 45326 | C95: 45326 | D95: NAKURU | E95: Nakuru | F95: John Mwangi | G95: John Mwangi | H95: P014 | I95: LED Bulb 9W (Pack of 4) | J95: Led Bulb 9W (Pack Of 4) | K95: 2 | L95: 2 | M95: 780 | N95: 780 | P95: 2 | Q95: 480 | R95: Electronics | S95: 1560 | T95: 960 | U95: 600 | V95: 0.38461538 | W95: Feb
A96: 10022 | B96: 45353 | C96: 45353 | D96: ELDORET | E96: Eldoret | F96: Aisha Hassan | G96: Aisha Hassan | H96: P005 | I96: Non-Stick Frying Pan 28cm | J96: Non-Stick Frying Pan 28Cm | K96: 1 | L96: 1 | M96: 1050 | N96: 1050 | P96: 1 | Q96: 700 | R96: Kitchenware | S96: 1050 | T96: 700 | U96: 350 | V96: 0.33333333 | W96: Mar
A97: 10006 | B97: 45299 | C97: 45299 | D97: Mombasa | E97: Mombasa | F97: John Mwangi | G97: John Mwangi | H97: P013 | I97: Kitchen Knife Set | J97: Kitchen Knife Set | K97: 6 | L97: 6 | M97: 1350 | N97: 1350 | P97: 6 | Q97: 800 | R97: Kitchenware | S97: 8100 | T97: 4800 | U97: 3300 | V97: 0.40740741 | W97: Jan
A98: 10314 | B98: 45361 | C98: 45361 | D98: Kisumu | E98: Kisumu | F98: Aisha Hassan | G98: Aisha Hassan | H98: P003 | I98: Rechargeable Torch RT-10 | J98: Rechargeable Torch Rt-10 | K98: 12 | L98: 12 | M98: 950 | N98: 950 | P98: 12 | Q98: 600 | R98: Electronics | S98: 11400 | T98: 7200 | U98: 4200 | V98: 0.36842105 | W98: Mar
A99: 10247 | B99: 45357 | C99: 45357 | D99: NAIROBI | E99: Nairobi | F99: Grace Achieng | G99: Grace Achieng | H99: P015 | I99: Water Dispenser Stand | J99: Water Dispenser Stand | K99: 5 | L99: 5 | M99: 2300 | N99: 2300 | P99: 5 | Q99: 1500 | R99: Household | S99: 11500 | T99: 7500 | U99: 4000 | V99: 0.34782609 | W99: Mar
A100: 10325 | B100: 45368 | C100: 45368 | D100: Eldoret | E100: Eldoret | F100: Peter Otieno | G100: Peter Otieno | H100: P002 | I100: solar lantern sl-200 | J100: Solar Lantern Sl-200 | K100: 12 | L100: 12 | M100: 1450 | N100: 1450 | P100: 12 | Q100: 900 | R100: Electronics | S100: 17400 | T100: 10800 | U100: 6600 | V100: 0.37931034 | W100: Mar
A101: 10283 | B101: 45354 | C101: 45354 | D101: Mombasa | E101: Mombasa | F101: Grace Achieng | G101: Grace Achieng | H101: P005 | I101: Non-Stick Frying Pan 28cm | J101: Non-Stick Frying Pan 28Cm | K101: 6 | L101: 6 | M101: 1100 | N101: 1100 | P101: 6 | Q101: 700 | R101: Kitchenware | S101: 6600 | T101: 4200 | U101: 2400 | V101: 0.36363636 | W101: Mar
... A105: 10207 | B105: 45342 | C105: 45342 | D105: NAKURU | E105: Nakuru | F105: John Mwangi | G105: John Mwangi | H105: P007 | I105: Mosquito Net - Family Size | J105: Mosquito Net - Family Size | K105: 20 | L105: 20 | M105: 700 | N105: 700 | P105: 20 | Q105: 400 | R105: Household | S105: 14000 | T105: 8000 | U105: 6000 | V105: 0.42857143 | W105: Feb
A106: 10154 | B106: 45371 | C106: 45371 | D106: Thika | E106: Thika | F106: Aisha Hassan | G106: Aisha Hassan | H106: P011 | I106: Padlock Set (3pc) | J106: Padlock Set (3Pc) | L106: 0 | M106: 650 | N106: 650 | P106: 0 | Q106: 450 | R106: Hardware | S106: 0 | T106: 0 | U106: 0 | V106: 0 | W106: Mar
...
